{"title":"지디넷코리아 ─ 뉴스 ─ 모바일","url":"https://zdnet.co.kr/news/?lstcode=0030&page=1","favicon":"https://zdnet.co.kr/news/favicon.ico","elements":[{"title":"30년전 인텔에 무슨일?…펜티엄 부동소수점 연산 오류 발견","contents":"1994년 6월 중순, 당시 미국 린치버그 칼리지(이후 린치버그 대학교로 승격) 수학과 교수였던 토머스 나이슬리(Thomas Ray Nicely) 박사는 연구실에서 인텔 펜티엄...","link":"https://zdnet.co.kr/view/?no=20241102230603","retrieved":1730595656917,"image":"https://zdnet.co.kr/images/default.png?ver=20220905"},{"title":"인도네시아, 아이폰16 이어 구글 픽셀폰도 판매 금지","contents":"인도네시아가 이번엔 구글 픽셀폰 판매를 금지했다고 로이터 등 외신들이 1일(현지시간) 보도했다. 이는 인도네시아 내에서 판매되는 스마트폰은 현지 제조 부품이 40% 이상 포함돼...","link":"https://zdnet.co.kr/view/?no=20241101203210","retrieved":1730517453812,"image":"https://zdnet.co.kr/images/default.png?ver=20220905"},{"title":"애플, 이미지 편집 앱 개발사 '픽셀메이터' 인수","contents":"애플이 인기 이미지 편집 앱 개발사 '픽셀메이터'(Pixelmator)를 인수하기로 했다고 나인투파이브맥 등 외신들이 1일(현지시간) 보도했다. 픽셀메이터는 블로그를 통해 이 ...","link":"https://zdnet.co.kr/view/?no=20241102071618","retrieved":1730508944603,"image":"https://zdnet.co.kr/images/default.png?ver=20220905"},{"title":"메타, 촉감을 느끼는 로봇 손 만든다…국내 업체도 참여","contents":"메타가 인공지능(AI)용 촉각 센서를 탑재한 정교한 로봇 손 개발을 위해 센서 전문 기업 젤사이트와 한국 로봇 기업 원익로보틱스와 협력한다고 밝혔다고 IT매체 테크크런치가 최근...","link":"https://zdnet.co.kr/view/?no=20241101145425","retrieved":1730508944603,"image":"https://zdnet.co.kr/images/default.png?ver=20220905"},{"title":"M4 맥으로 살펴본 차기 맥북 에어, 어떻게 나올까","contents":"이번 주 애플은 더 강력한 M4 칩을 탑재한 아이맥, 맥 미니, 맥북 프로 등 컴퓨터 신제품을 대거 출시했다. 이어 따라 애플 맥북 라인업 중 가장 대중적인 맥북 에어가 언제 ...","link":"https://zdnet.co.kr/view/?no=20241101154737","retrieved":1730502738740,"image":"https://zdnet.co.kr/images/default.png?ver=20220905"},{"title":"롯데하이마트, 3분기 영업익 312억원…전년比 13.8%↓","contents":"롯데하이마트는 지난 3분기 매출 6천859억원, 영업이익 312억원을 기록했다고 1일 공시했다. 전년 동기 대비 각각 5.5%, 13.8% 감소했다. 매출은 상반기 대비 감소폭...","link":"https://zdnet.co.kr/view/?no=20241101161250","retrieved":1730449022232,"image":"https://zdnet.co.kr/images/default.png?ver=20220905"},{"title":"유진로봇, 밀레 청소로봇 생산 중단...\"로봇에 집중\"","contents":"자율주행 솔루션 전문기업 유진로봇은 밀레 청소로봇 생산을 중단하고 기업 간 거래(B2B) 서비스 로봇 사업에 집중한다고 1일 공시했다. 유진로봇은 주문자개발생산(ODM) 방식으...","link":"https://zdnet.co.kr/view/?no=20241101155524","retrieved":1730449022233,"image":"https://zdnet.co.kr/images/default.png?ver=20220905"},{"title":"바디프랜드, 마사지 모듈 특허 3건 등록","contents":"헬스케어 가전기업 바디프랜드는 마사지 모듈 혁신 기술을 통해 사용자의 편의성 증진과 새로운 마사지 형태를 구현한 세 가지 기술을 특허 등록했다고 1일 밝혔다. 등록 특허는 바디...","link":"https://zdnet.co.kr/view/?no=20241101153149","retrieved":1730445184237,"image":"https://zdnet.co.kr/images/default.png?ver=20220905"},{"title":"쿠첸, 지마켓·옥션 '빅스마일데이' 참여…최대 30% 할인","contents":"주방가전기업 쿠첸은 오는 10일까지 지마켓과 옥션에서 진행하는 '빅스마일데이'에 참여해 브랜드관을 연다고 1일 밝혔다. 빅스마일데이는 지마켓과 옥션이 공동 진행하는 연중 최대 ...","link":"https://zdnet.co.kr/view/?no=20241101152504","retrieved":1730445184243,"image":"https://zdnet.co.kr/images/default.png?ver=20220905"},{"title":"에코백스, 로봇청소기 최대 35% 할인","contents":"로봇가전 전문 브랜드 에코백스는 오는10일까지 진행되는 'G마켓·옥션 빅스마일데이'와 11일까지 진행되는 '11번가 그랜드십일절'에 참여한다고 1일 밝혔다. 빅스마일데이와 그랜...","link":"https://zdnet.co.kr/view/?no=20241101152146","retrieved":1730445184250,"image":"https://zdnet.co.kr/images/default.png?ver=20220905"},{"title":"세라젬, 국가 브랜드 경쟁력 지수 1위 선정 기념 프로모션","contents":"헬스케어 가전기업 세라은 한국 생산성 본부가 발표하는 '국가 브랜드 경쟁력 지수(NBCI)' 1위 선정을 기념해 11월 한 달간 헬스케어 가전 제품 구매·렌탈 고객을 대상으로 ...","link":"https://zdnet.co.kr/view/?no=20241101150802","retrieved":1730441927301,"image":"https://zdnet.co.kr/images/default.png?ver=20220905"},{"title":"\"애플, 아이폰17부터 자체 개발 와이파이 칩 탑재\"","contents":"애플이 내년 가을 출시되는 아이폰17 시리즈부터 자체 개발한 와이파이(Wi-Fi) 7 칩을 사용할 것이라는 전망이 나왔다고 IT매체 애플인사이더가 31일(현지시간) 보도했다. ...","link":"https://zdnet.co.kr/view/?no=20241101135810","retrieved":1730441927307,"image":"https://zdnet.co.kr/images/default.png?ver=20220905"},{"title":"다이슨 블랙프라이데이…최대 35만원 할인","contents":"다이슨코리아는 오는 30일까지 블랙프라이데이 할인 프로모션을 진행한다고 1일 밝혔다. 프로모션은 다이슨 스토어와 공식 웹사이트를 포함, 백화점 내 다이슨 매장 등에서 진행된다....","link":"https://zdnet.co.kr/view/?no=20241101141509","retrieved":1730441927308,"image":"https://zdnet.co.kr/images/default.png?ver=20220905"},{"title":"코웨이 블랙프라이데이…\"렌탈료 반값 할인\"","contents":"종합 가전기업 코웨이는 블랙프라이데이를 앞두고 오는 27일까지 특별 프로모션을 진행한다고 1일 밝혔다. 코웨이는 행사 기간 동안 자사몰인 코웨이닷컴에서 제품을 구매하는 고객들에...","link":"https://zdnet.co.kr/view/?no=20241101140922","retrieved":1730438002344,"image":"https://zdnet.co.kr/images/default.png?ver=20220905"},{"title":"美 육군, 소총으로 무장한 '로봇개' 테스트…\"드론 폭파 목적\"","contents":"미국 육군이 무인 항공기를 총으로 격추할 수 있는 인공지능(AI) 로봇 개 테스트를 최근 사우디아라비아에서 실시했다고 IT매체 테크라이더가 31일(현지시간) 보도했다. 이 사족...","link":"https://zdnet.co.kr/view/?no=20241101132936","retrieved":1730438002345,"image":"https://zdnet.co.kr/images/default.png?ver=20220905"},{"title":"니콘이미징코리아, 고진영 선수와 '쿨샷' 전속모델 계약 연장","contents":"니콘이미징코리아는 1일 프로골퍼 고진영 선수와 골프 거리측정기 '쿨샷' 전속모델 계약을 연장했다고 밝혔다. 고진영 선수는 2018년 미국여자프로골프(LPGA) 첫 진출 이후 2...","link":"https://zdnet.co.kr/view/?no=20241101110713","retrieved":1730428057975,"image":"https://zdnet.co.kr/images/default.png?ver=20220905"},{"title":"한국레노버, 보급형 게임용 노트북 '로크 에센셜' 출시","contents":"한국레노버가 1일 게임과 학습, 일상 업무에 모두 활용할 수 있는 보급형 게임용 노트북 '로크 에센셜'(LOQ Essential)을 출시했다. 로크 에센셜은 12세대 인텔 코어...","link":"https://zdnet.co.kr/view/?no=20241101104822","retrieved":1730428057977,"image":"https://zdnet.co.kr/images/default.png?ver=20220905"},{"title":"AMD, 3D V캐시 탑재 '라이젠 7 9800X3D' 공개","contents":"AMD가 1일(미국시간 31일) 3D V캐시로 게임과 콘텐츠 제작 성능을 강화한 라이젠 7 9800X3D 프로세서를 공개했다. 라이젠 7 9800X3D 프로세서는 젠5(Zen ...","link":"https://zdnet.co.kr/view/?no=20241101103718","retrieved":1730428057984,"image":"https://zdnet.co.kr/images/default.png?ver=20220905"},{"title":"3Q 폰 시장 회복…애플 역대급 출하량에 삼성 아슬한 1위","contents":"스마트폰 시장이 다시 되살아나자 상위 5위 업체 간 경쟁이 치열해지고 있다. 중저가 시장을 키우는 애플은 1위 삼성전자를 빠르게 추격 중이다. 지난달 31일(현지시간) 시장조사...","link":"https://zdnet.co.kr/view/?no=20241101090811","retrieved":1730422870279,"image":"https://zdnet.co.kr/images/default.png?ver=20220905"},{"title":"삼성전자, '코리아세일페스타' 진행...148개 모델 할인","contents":"삼성전자가 대한민국 최대 쇼핑 축제인 '2024 코리아세일페스타'에 참가해 이달 1일부터 30일까지 한 달간 가전, 모바일, IT 제품 등을 할인한다. 삼성전자는 2016년부터...","link":"https://zdnet.co.kr/view/?no=20241101092915","retrieved":1730422870279,"image":"https://zdnet.co.kr/images/default.png?ver=20220905"}]}