{"title":"지디넷코리아 ─ 뉴스 ─ 최신 뉴스","url":"https://zdnet.co.kr/news/?lstcode=0000&page=1","favicon":"https://zdnet.co.kr/news/favicon.ico","elements":[{"title":"마이크로소프트, 자체 Arm CPU 기반 '코발트 VM' 출시","contents":"마이크로소프트가 자세 설계한 Arm 기반 CPU '애저 코발트100'에서 구동되는 '코발트 VM'을 출시했다. 21일(현지시간) 마이크로소프트는 미국 시애틀에서 개최된 연례 개...","link":"https://zdnet.co.kr/view/?no=20240521224930","retrieved":1716307964645,"image":"https://image.zdnet.co.kr/2023/11/16/213d87d8732eed8aa1cf4c15e5dbd94e-290x182.jpg"},{"title":"마이크로소프트, '깃허브 코파일럿 익스텐션' 출시","contents":"깃허브 코파일럿이 익스텐션 기능을 달고 워크플로우 통합 범위를 확장한다. 마이크로소프트는 21일(현지시간) 미국 시애틀에서 개최한 연례 개발자 컨퍼런스 '마이크로소프트 빌드 2...","link":"https://zdnet.co.kr/view/?no=20240521225229","retrieved":1716307964647,"image":"https://image.zdnet.co.kr/2024/05/20/24626bcb8917122f9a9cf5ae0d319841-290x182.png"},{"title":"마이크로소프트 코파일럿, 개인용에서 팀 도우미로 진화","contents":"마이크로소프트의 생성형 인공지능(AI) 기반 도구인 '마이크로소프트 코파일럿'을 팀 단위에서 함께 이용할 수 있게 됐다. 마이크로소프트는 21일(현지시간) 개최한 연례 개발자 ...","link":"https://zdnet.co.kr/view/?no=20240521225443","retrieved":1716307964649,"image":"https://zdnet.co.kr/images/default.png?ver=20220905"},{"title":"EU, 세계 첫 'AI법' 확정…이사회 최종 승인","contents":"세계 첫 인공지능(AI) 규제법으로 관심을 모으고 있는 유럽연합(EU)의 AI법이 마침내 최종 확정됐다. 유럽이사회는 21일(현지시간) AI법을 최종 승인했다고 테크크런치를 비...","link":"https://zdnet.co.kr/view/?no=20240521222654","retrieved":1716300553664,"image":"https://zdnet.co.kr/images/default.png?ver=20220905"},{"title":"AMD, 최대 16코어 서버용 프로세서 '에픽 4004' 시리즈 출시","contents":"AMD가 중소기업과 호스팅 기반 IT 서비스 업체를 겨냥한 서버용 프로세서 '에픽(EPYC) 4004' 시리즈를 출시했다. AMD는 2019년부터 데스크톱PC용 라이젠 프로세서...","link":"https://zdnet.co.kr/view/?no=20240521175459","retrieved":1716297148653,"image":"https://zdnet.co.kr/images/default.png?ver=20220905"},{"title":"한국바른채용인증원, 채용전문면접관 2급 자격과정 개최","contents":"채용인증기관 한국바른채용인증원(원장 조지용)은 제203회 채용전문면접관 2급 자격과정을 대전에서 6월5일 개최한다. 채용전문면접관 자격과정은 2018년 이후 3천여명의 인사채용...","link":"https://zdnet.co.kr/view/?no=20240521215715","retrieved":1716297148659,"image":"https://zdnet.co.kr/images/default.png?ver=20220905"},{"title":"한국IT서비스학회, 춘계학술대회 30일 개최···오세훈 시장 기조강연","contents":"한국IT서비스학회(회장 이정훈 연세대 정보대학원 교수)는 국제전자상거래연구원(ICEC, International Center for Electronic Commerce 원장 임...","link":"https://zdnet.co.kr/view/?no=20240521202711","retrieved":1716293896602,"image":"https://zdnet.co.kr/images/default.png?ver=20220905"},{"title":"하리수 건강 이상 호소 \"기침하면 갈비뼈까지 아프다\"","contents":"가수 겸 모델 하리수가 건강 이상을 호소했다. 하리수는 21일 소셜미디어에 \"이번 감기 진짜 오래가네. 지지난주 걸린 감기에 기침하면 갈비뼈까지 아프다\"고 호소했다. 그는 \"벌...","link":"https://zdnet.co.kr/view/?no=20240521200951","retrieved":1716289816075,"image":"https://zdnet.co.kr/images/default.png?ver=20220905"},{"title":"류수영, 알고보니 66억 성수동 '소금빵 맛집' 건물주","contents":"배우 류수영㊺이 건물주가 된 사실이 뒤늦게 확인됐다. 21일 한경닷컴 등 업계에 따르면, 류수영은 지난해 4월 자신이 대표로 있는 법인 이오커뮤니케이션 명의로 서울 성동구...","link":"https://zdnet.co.kr/view/?no=20240521200826","retrieved":1716289816077,"image":"https://zdnet.co.kr/images/default.png?ver=20220905"},{"title":"'용준형과 열애' 현아, 악플 테러 '불똥'...이유는?","contents":"가수 현아가 용준형과 교제한다는 이유로 악플 테러를 당하고 있다. 21일 현아 인스타그램 게시물엔 영어·일어·중국어로 적힌 악플이 다수 달렸다. 해외 누리꾼들은 \"버닝썬 BBC...","link":"https://zdnet.co.kr/view/?no=20240521200736","retrieved":1716289816081,"image":"https://zdnet.co.kr/images/default.png?ver=20220905"},{"title":"'비공개 출석' 김호중 \"변호사가 질의응답할 것\"","contents":"트로트 가수 김호중㉝이 음주 뺑소니 혐의 첫 경찰 조사를 받고 입장을 발표한다. 소속사 생각엔터테인먼트는 21일 \"김호중은 금일 오후 2시 강남경찰서에 출석했다. 출석 과...","link":"https://zdnet.co.kr/view/?no=20240521200619","retrieved":1716289816081,"image":"https://zdnet.co.kr/images/default.png?ver=20220905"},{"title":"한혜진, 홍천 별장 무단 침입에 긴급 공사...\"담장·대문 만들고 있다\"","contents":"한혜진이 홍천 별장에 대문과 담장을 짓고 있다고 밝혔다. 21일 한혜진은 자신의 유튜브 채널에서 70만 구독자 달성 기념 라이브 방송을 진행했다. 방송에서 한혜진은 \"홍천 별장...","link":"https://zdnet.co.kr/view/?no=20240521200519","retrieved":1716289816081,"image":"https://zdnet.co.kr/images/default.png?ver=20220905"},{"title":"넥슨 '던파 모바일', 中 출시 6시간 만에 매출 순위 1위","contents":"넥슨의 '던전앤파이터 모바일(던파 모바일)'이 중국 서비스를 시작한 가운데, 출시 6시간 만에 현지 앱 마켓 인기·매출 순위 1위를 달성했다. 모바일인덱스에 따르면, 던파 모바...","link":"https://zdnet.co.kr/view/?no=20240521175832","retrieved":1716282689084,"image":"https://zdnet.co.kr/images/default.png?ver=20220905"},{"title":"올마이투어닷컴, 1분기 매출 65억원…전년 比 2배 성장","contents":"글로벌 숙소 원가예약 플랫폼 올마이투어닷컴은 올해 1분기 매출이 64억9천만원을 기록하며 전년 동기(33억원) 대비 96% 성장했다고 21일 밝혔다. 1분기 영업 손실은 4천4...","link":"https://zdnet.co.kr/view/?no=20240521175330","retrieved":1716282689085,"image":"https://zdnet.co.kr/images/default.png?ver=20220905"},{"title":"공영홈쇼핑, '우수 아이디어 창의혁신 제품 공모전' 시상식 개최","contents":"공영홈쇼핑(대표 조성호)은 21일 서울 마포구 에스플렉스센터에서 '제3회 우수 아이디어 창의혁신 제품 공모전' 시상식을 개최했다. 공영홈쇼핑이 벤처·스타트업 등 혁신기업을 발굴...","link":"https://zdnet.co.kr/view/?no=20240521174145","retrieved":1716282689085,"image":"https://zdnet.co.kr/images/default.png?ver=20220905"},{"title":"세일포인트, 아이덴티티 보안 통합 지원 '고객 성공 센터' 출시","contents":"세일포인트 테크놀로지는 아이덴티티 보안 여정 전반을 지원하기 위해 디지털 '고객 성공 센터'를 출시했다고 21일 밝혔다. 세일포인트 고객 성공 센터는 파트너 및 고객사에 다양한...","link":"https://zdnet.co.kr/view/?no=20240521174836","retrieved":1716282689085,"image":"https://zdnet.co.kr/images/default.png?ver=20220905"},{"title":"과기정통부, 카톡 연속 장애에 현장점검 착수","contents":"과학기술정보통신부는 최근 연속해 발생한 카카오톡 장애에 대해 21일 긴급 현장점검에 착수했다고 밝혔다. 과기정통부는 소프트웨어, 네트워크 등 관련 분야 전문가와 함께 현장 조사...","link":"https://zdnet.co.kr/view/?no=20240521174215","retrieved":1716282689088,"image":"https://zdnet.co.kr/images/default.png?ver=20220905"},{"title":"아스펜테크, 아람코와 온실가스 배출 완화 기술 투자 지원","contents":"아스펜테크가 기업들의 온실가스 배출 완화 기술에 투자를 유도하기 위한 지원에 나선다. 아스펜테크 코리아(대표 김흥식)는 '지속가능성 경로를 위한 아스펜테크 전략 계획을 발표했다...","link":"https://zdnet.co.kr/view/?no=20240521173354","retrieved":1716282689090,"image":"https://zdnet.co.kr/images/default.png?ver=20220905"},{"title":"재재, '두시의 데이트' DJ 1년 만에 하차…후임 미정","contents":"방송인 재재가 MBC FM4U '두시의 데이트 재재입니다' DJ 자리에서 아쉽게 물러난다. 21일 MBC는 이 같은 소식을 밝히며 \"1년 여 동안 함께한 DJ 재재는 향후 계획...","link":"https://zdnet.co.kr/view/?no=20240521172609","retrieved":1716282689092,"image":"https://zdnet.co.kr/images/default.png?ver=20220905"},{"title":"식약처, 항불안제 등 사망자 명의도용 처방 의심자 방문 의료기관 18개소 점검","contents":"식품의약품안전처는 경찰청‧지방자치단체와 함께 의료용 마약류의 처방·사용에 대한 불법취급을 예방하고자 요양병원 등 의료기관 18개소에 대한 기획합동점검을 21일부터 31일까지 실...","link":"https://zdnet.co.kr/view/?no=20240521172256","retrieved":1716282689096,"image":"https://zdnet.co.kr/images/default.png?ver=20220905"}]}