{"title":"지디넷코리아 ─ 뉴스 ─ 최신 뉴스","url":"https://zdnet.co.kr/news/?lstcode=0000&page=1","favicon":"https://zdnet.co.kr/news/favicon.ico","elements":[{"title":"포드, 신형 레인저 출시…6350만원부터","contents":"포드코리아는 새롭게 업그레이드된 넥스트 제너레이션 포드 레인저를 한국 시장에 공식 출시한다고 2일 밝혔다. 레인저는 포드자동차의 대표적 중형 픽업트럭으로 전 세계 180여개 국...","link":"https://zdnet.co.kr/view/?no=20230302131027","retrieved":1677737657556,"image":"https://image.zdnet.co.kr/2023/03/02/32da4bb4992b4e25faa6e6385f93b320-290x182.jpg"},{"title":"라인게임즈 '대항해시대 오리진', 3월 7일 글로벌 서비스 시작","contents":"라인게임즈(대표 박성민)는 2일 모티프(대표 이득규)와 코에이테크모게임스(대표 코이누마 히사시)가 공동 개발하고 자사가 서비스하는 오픈월드 MMORPG '대항해시대 오리진'이 ...","link":"https://zdnet.co.kr/view/?no=20230302145708","retrieved":1677737657564,"image":"https://image.zdnet.co.kr/2023/03/02/0e4a1e0fd52dd177e7eaf6cbe8bb5e0a-290x182.jpg"},{"title":"캐논코리아, 4월 말까지 RF렌즈 정품등록 행사 진행","contents":"캐논코리아가 오는 4월 말까지 미러리스 카메라용 RF 렌즈 23종 대상 정품등록 행사를 진행한다. 행사 대상 제품은 광각 줌렌즈 'RF15-30mm F4.5-6.3 IS STM...","link":"https://zdnet.co.kr/view/?no=20230302150401","retrieved":1677737657569,"image":"https://zdnet.co.kr/images/default.png?ver=20220905"},{"title":"니콘이미징코리아, 거리측정기 '쿨샷' 보증기간 연장","contents":"니콘이미징코리아가 오는 5월 말까지 골프 거리측정기 '쿨샷' 보증기간 연장 행사를 진행한다. 대상 제품은 쿨샷 프로Ⅱ 스테빌라이즈드, 쿨샷 라이트 스테빌라이즈드, 쿨샷 50i,...","link":"https://zdnet.co.kr/view/?no=20230302145914","retrieved":1677737657570,"image":"https://zdnet.co.kr/images/default.png?ver=20220905"},{"title":"KB국민은행, 자립 준비 청년 '버팀목' 된다","contents":"KB국민은행은 자립을 준비하는 청년을 지원하는 프로그램을 가동한다고 2일 밝혔다. 자립 준비 청년은 만 18세가 되면 복지 시설 등을 떠나 사회로 나오는 청년을 의미한다. KB...","link":"https://zdnet.co.kr/view/?no=20230302142403","retrieved":1677737657573,"image":"https://zdnet.co.kr/images/default.png?ver=20220905"},{"title":"이마트, 4월 3일부터 오후 10시에 영업 종료","contents":"이마트가 4월 3일부터 전국 점포의 영업 종료 시간을 종전 오후 11시에서 10시로 조정한다고 2일 밝혔다. 이는 야간에 매장을 찾는 고객의 비중이 줄어든 배경이라고 이마트 측...","link":"https://zdnet.co.kr/view/?no=20230302141532","retrieved":1677737657577,"image":"https://zdnet.co.kr/images/default.png?ver=20220905"},{"title":"웰컴저축은행, '1사1교 금융교육' 우수금융사 직원상 수상","contents":"웰컴저축은행은 금융소비자보호팀 장민희 차장이 1사 1교 금융교육 우수 금융회사 직원으로 선정돼 저축은행중앙회장상을 받았다고 2일 밝혔다. 웰컴저축은행은 사회 초년생들이 유의해야...","link":"https://zdnet.co.kr/view/?no=20230302142451","retrieved":1677737657578,"image":"https://zdnet.co.kr/images/default.png?ver=20220905"},{"title":"정부, 산업 디지털전환 R&D에 2025년까지 610억 투입","contents":"정부가 산업 디지털전환 연구개발(R&amp;D)에 2025년까지 610억원을 지원한다. 산업통상자원부는 인공지능(AI)을 활용하는 철강·자동차 등 수요기업과 AI 솔루션을 공급하는 기...","link":"https://zdnet.co.kr/view/?no=20230302142805","retrieved":1677737657580,"image":"https://zdnet.co.kr/images/default.png?ver=20220905"},{"title":"컴투스홀딩스, 신작 '제노니아' 티저사이트 오픈...상반기 출시 목표","contents":"컴투스홀딩스(대표 이용국)는 상반기 출시 예정인 대작 MMORPG '제노니아'의 티저 사이트를 오픈했다고 2일 밝혔다. 티저 사이트에서는 글로벌 히트 IP '제노니아'의 역사를...","link":"https://zdnet.co.kr/view/?no=20230302100652","retrieved":1677737657582,"image":"https://zdnet.co.kr/images/default.png?ver=20220905"},{"title":"\"서울시, 디지털 선도 도시로 '우뚝'...노하우 배우러 해외서 줄 섭니다\"","contents":"\"1천만 모든 서울 시민이 디지털 사용에 불편함이 없도록 디지털 약자와의 동행을 지속적으로 확대할 계획입니다. 또한 서울을 디지털 대전환을 통한 국제적인 스마트시티로 변모시켜 ...","link":"https://zdnet.co.kr/view/?no=20230301193032","retrieved":1677737657584,"image":"https://zdnet.co.kr/images/default.png?ver=20220905"},{"title":"미버스랩스, 블록체인 솔루션 기업 '해치랩스'와 MOU","contents":"미투젠(대표 손창욱)은 2일 자회사 미버스랩스(대표 홍종호)가 국내외 블록체인 생태계 확장을 위해 블록체인 솔루션 전문 IT기업인 '해치랩스'와 업무 협약을 맺고 메인넷 연동 ...","link":"https://zdnet.co.kr/view/?no=20230302141046","retrieved":1677737657586,"image":"https://zdnet.co.kr/images/default.png?ver=20220905"},{"title":"코스포, 첫 백서 발간…정기 대의원총회서 공개","contents":"코리아스타트업포럼이 출범 7년차를 맞아 지난해 주요 활동과 성과를 총망라한 백서를 발간했다고 2일 밝혔다. 코스포는 지난달 28일 서울 강남 드림플러스에서 진행한 2023년도 ...","link":"https://zdnet.co.kr/view/?no=20230302135104","retrieved":1677733846235,"image":"https://zdnet.co.kr/images/default.png?ver=20220905"},{"title":"NH농협생명, '농업인NH안전보험' 개정 출시","contents":"NH농협생명은 농업인NH안전보험을 개정 출시했다고 2일 밝혔다. 우선 농업인NH안전보험(무) 일반2형·3형의 경우, 최대 가입 나이를 기존 84세에서 87세까지로 확대했다. 주...","link":"https://zdnet.co.kr/view/?no=20230302114122","retrieved":1677733846239,"image":"https://zdnet.co.kr/images/default.png?ver=20220905"},{"title":"넥슨 베일드엑스퍼트, 파이널 테스트 사전신청","contents":"넥슨코리아(대표 이정헌)는 자회사 넥슨게임즈(대표 박용현)에서 개발 중인 PC 슈팅 게임 '베일드 엑스퍼트(VEILED EXPERTS)'의 넥슨닷컴 서비스를 오픈하고 파이널 베...","link":"https://zdnet.co.kr/view/?no=20230302100409","retrieved":1677733846243,"image":"https://zdnet.co.kr/images/default.png?ver=20220905"},{"title":"신한카드, 포용적 금융교육으로 금감원장상 수상","contents":"신한카드는 금융감독원이 주관하는 '1사1교 금융교육 우수 사례 시상식'에서 우수 금융회사 부문 '금융감독원장상'을 수상했다고 2일 밝혔다. 금융감독원이 운영하는 '1사1교 금융...","link":"https://zdnet.co.kr/view/?no=20230302113333","retrieved":1677733846247,"image":"https://zdnet.co.kr/images/default.png?ver=20220905"},{"title":"티맥스티베로, 하이퍼SQL 제품명 '티맥스 오픈SQL'로 변경","contents":"티맥스티베로가 자사 오픈소스 DBMS 플랫폼 '하이퍼SQL'제품명을 '티맥스 오픈SQL'로 변경했다고 2일 밝혔다. 티맥스 오픈SQL은 기업 비즈니스 환경에 맞춰 오픈소스와 상...","link":"https://zdnet.co.kr/view/?no=20230302123759","retrieved":1677733846252,"image":"https://zdnet.co.kr/images/default.png?ver=20220905"},{"title":"삼성화재·벨포코리아 '긴급복구서비스 파트너십' MOU 체결","contents":"삼성화재는 벨포코리아와 '긴급복구서비스 파트너십'에 관한 업무협약(MOU)을 체결했다고 2일 밝혔다. 이번 협약으로 양사는 삼성화재 고객사의 사고로 인한 손해를 최소화하고, 조...","link":"https://zdnet.co.kr/view/?no=20230302112713","retrieved":1677733846255,"image":"https://zdnet.co.kr/images/default.png?ver=20220905"},{"title":"아이템베이, 사내 친환경 문화 캠페인 '베착템' 실시","contents":"창립 22주년을 맞은 아이템 거래 플랫폼 아이템베이가 ESG 경영 강화를 위한 사내 친환경 캠페인 '베착템'을 실시한다고 2일 밝혔다. 베착템 캠페인은 '베이의 착한 아이템'의...","link":"https://zdnet.co.kr/view/?no=20230302100054","retrieved":1677730402641,"image":"https://zdnet.co.kr/images/default.png?ver=20220905"},{"title":"'책임 있는 AI' 제작·활용 가이드라인 나왔다...오픈AI도 참여","contents":"오픈AI를 비롯한 10개 기업이 인공지능(AI) 콘텐츠를 책임 있게 구축, 공유하자는 가이드라인을 제시했다. 생성 AI 제작이 윤리적으로 이뤄지고, AI로 인한 개인정보 유출 ...","link":"https://zdnet.co.kr/view/?no=20230302105900","retrieved":1677730402649,"image":"https://zdnet.co.kr/images/default.png?ver=20220905"},{"title":"대한상의, '상공의 날 50년' 맞아 릴레이 기념행사 개최","contents":"대한상공회의소가 상공인들의 고민과 해법을 공유하는 자리를 마련한다. 한국경제를 빛낸 상공인 200여명에 정부 표창을 주고, 일반인을 위한 '50자 백일장', '빌딩숲 음악회'도...","link":"https://zdnet.co.kr/view/?no=20230302094443","retrieved":1677727208731,"image":"https://zdnet.co.kr/images/default.png?ver=20220905"}]}