{"title":"지디넷코리아 ─ 뉴스 ─ 카테크","url":"https://zdnet.co.kr/news/?lstcode=0057&page=1","favicon":"https://zdnet.co.kr/news/favicon.ico","elements":[{"title":"KGM 첫 전기 픽업 '무쏘 EV' 가격 확정…4800만원부터","contents":"KG모빌리티(KGM)가 '무쏘 EV'의 친환경차 국고 보조금이 확정됨에 따라 판매 가격을 18일 공개했다. '무쏘 EV'는 국내 최초의 전기 픽업으로 전기 SUV의 편안함과 경...","link":"https://zdnet.co.kr/view/?no=20250218144855","retrieved":1739859506167,"image":"https://zdnet.co.kr/images/default.png?ver=20220905"},{"title":"기아, 고성능 'EV9 GT' 계약 개시…8849만원","contents":"기아가 플래그십 전동화 SUV EV9의 고성능 모델인 '더 기아 EV9 GT(The Kia EV9 GT, 이하 EV9 GT)'와 실용성과 경제성을 갖춘 '스탠다드' 모델의 계약...","link":"https://zdnet.co.kr/view/?no=20250218133647","retrieved":1739855627830,"image":"https://zdnet.co.kr/images/default.png?ver=20220905"},{"title":"국내 18% 점유율 수입차…30년간 대변해온 'KAIDA'","contents":"한국수입자동차협회(KAIDA)는 설립 30주년을 기념하여 엠블럼 제작과 함께 '혁신과 다양성으로 여는 미래'를 슬로건으로 채택하고 소비자 인식조사, 사진 공모전, 기획 통계 발...","link":"https://zdnet.co.kr/view/?no=20250218131802","retrieved":1739855627833,"image":"https://zdnet.co.kr/images/default.png?ver=20220905"},{"title":"테슬라 모델S보다 2초 빨랐다…현대차 아이오닉5 N, 日 대회 신기록","contents":"현대자동차는 지난 15일 일본 츠쿠바 서킷 코스 2000에서 개최되는 '어택 츠쿠바(Attack Tsukuba) 2025'의 '레이싱카 &amp; 슬릭타이어 클래스'에서 아이오닉 5 ...","link":"https://zdnet.co.kr/view/?no=20250218130129","retrieved":1739852127141,"image":"https://zdnet.co.kr/images/default.png?ver=20220905"},{"title":"현대차, '2025 더 뉴 마이티' 출시…에어 서스 시트 탑재","contents":"현대자동차가 상품 경쟁력을 높인 대표 준중형 트럭 '2025 더 뉴 마이티'를 18일 출시하고 본격적인 판매에 돌입한다고 밝혔다. 2025 더 뉴 마이티는 상용 고객의 목소리를...","link":"https://zdnet.co.kr/view/?no=20250218123926","retrieved":1739852127145,"image":"https://zdnet.co.kr/images/default.png?ver=20220905"},{"title":"현대차, 지역 미술 활성화 '현대 트랜스로컬 시리즈' 공개","contents":"현대자동차가 예술 생태계 발전을 지원하기 위해 국내 공공 예술 기관의 국제 교류 및 협업을 기반으로 하는 신규 파트너십 '현대 트랜스로컬 시리즈(Hyundai Transloca...","link":"https://zdnet.co.kr/view/?no=20250218123135","retrieved":1739852127146,"image":"https://zdnet.co.kr/images/default.png?ver=20220905"},{"title":"미중 갈등에 낀 테슬라…FSD 중국 출시 지연되나","contents":"테슬라 완전자율주행(FSD) 시스템의 중국 출시가 지연될 수 있다는 가능성이 제기됐다. 17일(현지시간) 전기차 전문매체 일렉트렉, 테슬라라티 등은 미중 무역갈등이 고조되는 가...","link":"https://zdnet.co.kr/view/?no=20250218090757","retrieved":1739840211978,"image":"https://zdnet.co.kr/images/default.png?ver=20220905"},{"title":"이탈리아보다 람보르기니 많이 사는 한국…회장 날아온다","contents":"'487대 vs 479대' 지난해 한국과 이탈리아에서 팔린 람보르기니 판매량이다. 람보르기니의 한국 판매량이 본국인 이탈리아를 처음 추월한 것은 2023년이다. 이후 2년 연속...","link":"https://zdnet.co.kr/view/?no=20250217152151","retrieved":1739780272887,"image":"https://zdnet.co.kr/images/default.png?ver=20220905"},{"title":"정의선 회장, 작년 우승한 기아 타이거즈 美 훈련장 '깜짝 방문'","contents":"현대자동차그룹 정의선 회장이 미국 출장 중에 현지의 KIA 타이거즈 스프링캠프를 깜짝 방문했다. 정의선 회장은 현지시간 16일 미 캘리포니아 어바인 인근에 위치한 더 클럽하우스...","link":"https://zdnet.co.kr/view/?no=20250217133831","retrieved":1739769320592,"image":"https://zdnet.co.kr/images/default.png?ver=20220905"},{"title":"렉서스 '디 올 뉴 LX700h' 사전계약…1억6587만원부터","contents":"렉서스코리아는 플래그십 대형 SUV인 '디 올 뉴 LX 700h(The All-New LX 700h)'를 공식 출시하고 전국 렉서스 공식 딜러 전시장에서 17일부터 사전 계약을...","link":"https://zdnet.co.kr/view/?no=20250217102916","retrieved":1739758787640,"image":"https://zdnet.co.kr/images/default.png?ver=20220905"},{"title":"현대위아, 중동 찾아 '모빌리티 기반 화포체계' 공개","contents":"현대위아가 중동·아프리카 지역 최대 규모 방위산업 전시회에서 모빌리티 기반 화포체계를 선보였다. 현대위아는 아랍에미리트(UAE) 아부다비 국제 전시센터에서 개최하는 'IDEX ...","link":"https://zdnet.co.kr/view/?no=20250217100931","retrieved":1739758787641,"image":"https://zdnet.co.kr/images/default.png?ver=20220905"},{"title":"기아, 중동·아프리카 최대 방산 전시회서 '군용 타스만' 공개","contents":"기아가 아프리카·중동 지역 최대 규모의 국제 방산 전시회에 참여해 브랜드 최초 전통 픽업 '타스만'을 아중동 고객의 니즈를 반영한 특수 사양을 적용해 전시했다. 기아가 17일부...","link":"https://zdnet.co.kr/view/?no=20250217100216","retrieved":1739758787642,"image":"https://zdnet.co.kr/images/default.png?ver=20220905"},{"title":"포티투닷-신세계프라퍼티, 화성 스타베이에 자율주행 도심교통 조성","contents":"현대자동차그룹 포티투닷이 신세계프라퍼티와 사용자 중심의 지속 가능한 스마트시티 조성에 나선다고 17일 밝혔다. 포티투닷은 지난 14일 신세계프라퍼티와 화성 스타베이 시티 내 자...","link":"https://zdnet.co.kr/view/?no=20250217094400","retrieved":1739753955494,"image":"https://zdnet.co.kr/images/default.png?ver=20220905"},{"title":"IT 공룡 총출동 세계 최대 모빌리티쇼, 삼성전자·LG엔솔 등 韓기업 출격","contents":"세계 최대 모빌리티 전시회 IAA 2025에 국내외 주요 기업들이 대거 참가한다. 17일 IAA에 따르면 'It's All About Mobility'라는 슬로건 하에 열리는 ...","link":"https://zdnet.co.kr/view/?no=20250217090901","retrieved":1739753955494,"image":"https://zdnet.co.kr/images/default.png?ver=20220905"},{"title":"현대차그룹 대학생 교육봉사단 'H-점프스쿨' 12기 발대식","contents":"현대자동차그룹이 대학생 사회공헌 프로그램 'H-점프스쿨' 12기 발대식을 진행했다고 17일 밝혔다. 13일부터 14일까지 연세대 국제캠퍼스(인천 송도 소재)에서 열린 발대식에는...","link":"https://zdnet.co.kr/view/?no=20250217091430","retrieved":1739753955496,"image":"https://zdnet.co.kr/images/default.png?ver=20220905"},{"title":"기아, 최초 전기 세단 'EV4' 디자인 공개…\"네번째 전기차 모델\"","contents":"기아가 브랜드 최초 전동화 세단 '더 기아 EV4(The Kia EV4, 이하 EV4)'의 외장 디자인을 17일 공개했다. EV4는 21년 출시된 기아의 첫 전용 전기차 EV6...","link":"https://zdnet.co.kr/view/?no=20250217090912","retrieved":1739753955497,"image":"https://zdnet.co.kr/images/default.png?ver=20220905"},{"title":"1년만에 10만대 돌파…전기트럭 대신 'LPG 1톤 트럭' 찾는 이유는","contents":"신형 LPG 1톤 트럭이 출시 1년여 만에 판매대수 10만 대를 돌파했다. 대한LPG협회는 현대차 포터2, 기아 봉고3 LPG 모델의 누적 판매대수가 올해 1월말 기준 10만2...","link":"https://zdnet.co.kr/view/?no=20250216142121","retrieved":1739686570993,"image":"https://zdnet.co.kr/images/default.png?ver=20220905"},{"title":"캐나다 홀린 '아이오닉5N·싼타페'…현대차, 올해의 차 2개 부문 석권","contents":"현대자동차는 캐나다 토론토에서 열린 캐나다 국제 오토쇼에서 '2025 캐나다 올해의 유틸리티 차'에 싼타페가, '2025 캐나다 올해의 전기차 유틸리티'에 아이오닉 5 N이 각...","link":"https://zdnet.co.kr/view/?no=20250216141303","retrieved":1739686570997,"image":"https://zdnet.co.kr/images/default.png?ver=20220905"},{"title":"[타보고서] 주행성능 완벽 '푸조 e2008'…도심형 소형 전기 SUV","contents":"4미터(m)가 조금 넘는 길이의 소형 스포츠유틸리티차(SUV)에 길을 지나면 한번쯤 돌아보게 하는 유니크한 디자인, 전기차 특유의 가속감을 갖추고 오랜 모터스포츠 노하우가 담긴...","link":"https://zdnet.co.kr/view/?no=20250216013435","retrieved":1739679304838,"image":"https://zdnet.co.kr/images/default.png?ver=20220905"},{"title":"전기차가 200만원대?…中 젠지 사로잡은 베스튠 포니 '화제'","contents":"중국에서 200만원대로 소형 전기차를 구매할 수 있어 화제를 모으고 있다. 16일 업계에 따르면 중국에는 100개가 넘는 전기차 업체가 있다. 이 중에서도 소형 전기차 업체들은...","link":"https://zdnet.co.kr/view/?no=20250214162633","retrieved":1739667691577,"image":"https://zdnet.co.kr/images/default.png?ver=20220905"}]}