{"title":"지디넷코리아 ─ 뉴스 ─ 컴퓨팅","url":"https://zdnet.co.kr/news/?lstcode=0020&page=1","favicon":"https://zdnet.co.kr/news/favicon.ico","elements":[{"title":"\"AI 기술을 가장 쉽고 안전하게 활용할 수 있는 플랫폼”","contents":"“레드햇이 한국에 존재하는 이유는 한국 고객의 경쟁력 강화에 기여하기 위해서다. 현재 고객의 경쟁력 강화를 위한 논의는 인공지능(AI)에 있다. 레드햇은 엔터프라이즈 AI 플랫...","link":"https://zdnet.co.kr/view/?no=20240401104740","retrieved":1711936521260,"image":"https://zdnet.co.kr/images/default.png?ver=20220905"},{"title":"美 피델리티, 보유 엑스 지분 가치 73% 하락","contents":"미국의 글로벌 자산운용사 피델리티가 보유한 엑스(X, 구 트위터)의 지분 가치가 73% 하락한 것으로 예측됐다. 31일(현지시간) 블룸버그 통신에 따르면 피델리티의 블루칩 그로...","link":"https://zdnet.co.kr/view/?no=20240401093127","retrieved":1711936521262,"image":"https://zdnet.co.kr/images/default.png?ver=20220905"},{"title":"英 옥스퍼드, 환자에 약 추천·복용법 알리는 챗봇 공개","contents":"환자 상태에 맞는 약을 처방해 주는 인공지능(AI) 챗봇이 나왔다. 약을 복용하는 이유와 투약법, 부작용까지 알려줘 환각현상을 최소화했다. 31일 영국 가디언은 옥스퍼드대 AI...","link":"https://zdnet.co.kr/view/?no=20240401093457","retrieved":1711936521263,"image":"https://zdnet.co.kr/images/default.png?ver=20220905"},{"title":"구글, 러스트가 C++보다 생산성 2배 높아","contents":"구글은 러스트가 C++보다 안정성 뿐 아니라 생산성면에서도 뛰어나다고 강조했다. 31일 더레지스터 등 외신에 따르면 구글 라스 버그스트롬 엔지니어링 이사는 런던에서 열린 러스트...","link":"https://zdnet.co.kr/view/?no=20240401101734","retrieved":1711936521266,"image":"https://zdnet.co.kr/images/default.png?ver=20220905"},{"title":"에스넷시스템, OT 전용 솔루션 3종 출시","contents":"에스넷시스템(대표 유홍준, 장병강)이 운영기술(OT) 전용 솔루션 3종을 선보였다. 에스넷시스템은 시스코와 함께 '2024 스마트공장·자동화산업전'을 참가했다고 1일 밝혔다. ...","link":"https://zdnet.co.kr/view/?no=20240401103946","retrieved":1711936521268,"image":"https://zdnet.co.kr/images/default.png?ver=20220905"},{"title":"안랩, 중동 보안 시장 개척 '청신호'…사우디 '사이트'와 JV 설립","contents":"안랩이 중동 시장에서 보안 수출 청신호를 켰다. 사우디아라비아를 시작으로 점차 주변 중동 국가까지 외연을 넓히겠다는 전략이다. 안랩이 사우디아라비아 국영기업 '사이트(SITE,...","link":"https://zdnet.co.kr/view/?no=20240401100312","retrieved":1711936521269,"image":"https://zdnet.co.kr/images/default.png?ver=20220905"},{"title":"美 하원 \"마이크로소프트 코파일럿, 보안 취약…사용 금지\"","contents":"미국 하원이 데이터 유출 우려로 생성형 인공지능(AI) 서비스 '마이크로소프트 코파일럿' 사용을 전면 차단한다. 이에 마이크로소프트 측은 올 연말께 정부용 코파일럿 서비스를 출...","link":"https://zdnet.co.kr/view/?no=20240401095606","retrieved":1711936521270,"image":"https://zdnet.co.kr/images/default.png?ver=20220905"},{"title":"한컴 '투톱' 변성준·김연수 \"올해 AI 사업 본격화, 글로벌 빅테크 기업 도약\"","contents":"\"올해는 한글과컴퓨터가 AI 사업을 본격화하는 원년이자 글로벌 빅테크 기업으로 도약하기 위한 첫걸음을 떼는 매우 중요한 시점입니다.\" 변성준, 김연수 한컴 대표는 1일 '202...","link":"https://zdnet.co.kr/view/?no=20240401101745","retrieved":1711936521271,"image":"https://zdnet.co.kr/images/default.png?ver=20220905"},{"title":"JB금융 손 잡은 웹케시, 300억 투자해 국내외 핀테크 시장 공략 속도","contents":"웹케시그룹이 JB금융그룹과 손잡고 국내외 핀테크 시장 공략에 속도를 낸다. 웹케시그룹은 최근 JB금융그룹과 전략적 투자 계약을 체결했다고 1일 밝혔다. 이는 JB금융그룹의 '비...","link":"https://zdnet.co.kr/view/?no=20240401100731","retrieved":1711936521273,"image":"https://zdnet.co.kr/images/default.png?ver=20220905"},{"title":"신한은행 '쏠뱅크' 체감속도 4배 빨라진 이유는?","contents":"LG CNS가 자체 개발한 시스템 검증 솔루션 '퍼펙트윈(PerfecTwin)'을 앞세워 신한은행의 차세대 시스템 안정화 작업을 위한 해결사로 나섰다. LG CNS는 기존 신한...","link":"https://zdnet.co.kr/view/?no=20240401094711","retrieved":1711936521274,"image":"https://zdnet.co.kr/images/default.png?ver=20220905"},{"title":"할리우드에 구애 나선 샘 알트먼…오픈AI, '소라' 고객 확보 본격화","contents":"오픈AI가 동영상 생성 인공지능(AI) 기술인 '소라'의 정식 출시를 앞두고 할리우드 시장을 공략하기 위해 본격 나섰다. 1일 파이낸셜타임스에 따르면 샘 알트먼 오픈AI 최고경...","link":"https://zdnet.co.kr/view/?no=20240401092453","retrieved":1711932382854,"image":"https://zdnet.co.kr/images/default.png?ver=20220905"},{"title":"클라우데라, AI 시대 데이터 아키텍처 전략 발표","contents":"클라우데라는 'AI 시대의 데이터 아키텍처와 전략' 설문조사 결과를 1일 발표했다. 클라우데라의 의뢰로 파운드리에서 실시한 이 설문조사는 600명 이상의 데이터 분야 리더와 I...","link":"https://zdnet.co.kr/view/?no=20240401085034","retrieved":1711932382856,"image":"https://zdnet.co.kr/images/default.png?ver=20220905"},{"title":"워크데이, 아태지역 리테일 기업 고객 확장","contents":"워크데이는 자사의 리테일 및 레저 부문 비즈니스의 연간 반복 매출(ARR)이 10억 달러를 돌파했다고 1일 밝혔다. 이솝, 찰스앤키스, 한국콜마홀딩스, 몬델리즈, 무신사, 푸마...","link":"https://zdnet.co.kr/view/?no=20240401084123","retrieved":1711932382857,"image":"https://zdnet.co.kr/images/default.png?ver=20220905"},{"title":"어도비 파이어플라이, '구조 참조' 역량 추가","contents":"어도비는 이미지 생성형 인공지능(AI) 기능인 어도비 파이어플라이 웹 애플리케이션의 텍스트를 이미지로(Text to Image) 모듈에 구조 참조(Structure Refere...","link":"https://zdnet.co.kr/view/?no=20240401083746","retrieved":1711932382857,"image":"https://zdnet.co.kr/images/default.png?ver=20220905"},{"title":"美 AT&T, 7300만 고객정보 다크웹으로 유출됐다","contents":"미국 통신 대기업 AT&amp;T의 약 7천만명에 달하는 고객정보가 다크웹으로 유출됐다. 30일(현지시간) 블룸버그 통신 등 복수의 외신에 따르면 AT&amp;T는 계정 사용자 760만명을 ...","link":"https://zdnet.co.kr/view/?no=20240331151716","retrieved":1711872786780,"image":"https://zdnet.co.kr/images/default.png?ver=20220905"},{"title":"작년 스미싱 발생 50만건 육박...\"내 폰 카메라 제어까지?","contents":"지난해 국내에서 발생한 스미싱 탐지 건수가 50만3천300건으로 집계됐다. 특히 같은 기간 스미싱 악성앱 탐지·분석 건수는 3천761건에 달하는 것으로 조사됐다. 한국인터넷진흥...","link":"https://zdnet.co.kr/view/?no=20240329151113","retrieved":1711865503550,"image":"https://zdnet.co.kr/images/default.png?ver=20220905"},{"title":"오픈AI, 목소리 복제하는 '보이스 엔진' 미리보기 공개","contents":"오픈AI가 음성을 복제할 수 있는 인공지능(AI) 모델을 공개했다. 현재 소수 테스터들만 해당 모델에 접근할 수 있다. 29일 벤처비트는 오픈AI가 AI 음성 모델 '보이스 엔...","link":"https://zdnet.co.kr/view/?no=20240331092943","retrieved":1711849894577,"image":"https://zdnet.co.kr/images/default.png?ver=20220905"},{"title":"MS-오픈AI, 135조 규모 AI 슈퍼컴퓨터 개발...전용칩만 수백만개","contents":"챗GPT를 만든 오픈AI와 마이크로소프트가 최대 1000억 달러(약 135조 원)를 투자해 인공지능(AI)전용 슈퍼컴퓨터를 만든다. 최근 디인포메이션 등 외신은 마이크로소프트와...","link":"https://zdnet.co.kr/view/?no=20240331082358","retrieved":1711845979256,"image":"https://zdnet.co.kr/images/default.png?ver=20220905"},{"title":"\"PC 복구 기업? NO\"...솔루세움, 클라우드 보안 기업으로 진화","contents":"'킴수키', '라자루스'는 최근 대법원을 비롯해 국내 핵심 공공 정보망을 뒤흔든 해커조직이다. 과거 보안은 단편적인 영역에 불과했지만 이제는 무결점을 뜻하는 제로트러스트로까지 ...","link":"https://zdnet.co.kr/view/?no=20240326145835","retrieved":1711768409995,"image":"https://zdnet.co.kr/images/default.png?ver=20220905"},{"title":"'알파고 대부' 데미스 하사비스, 기사 작위 받았다","contents":"'알파고 대부'인 데미스 하사비스가 영국에서 기사 작위를 받는다. 데미스 하사비스 구글 딥마인드 최고경영자(CEO)가 인공지능에 기여한 공을 인정받아 영국에서 기사 작위를 받게...","link":"https://zdnet.co.kr/view/?no=20240330094227","retrieved":1711762762484,"image":"https://zdnet.co.kr/images/default.png?ver=20220905"}]}