{"title":"지디넷코리아 ─ 중기&스타트업","url":"https://zdnet.co.kr/news/?lstcode=0045&page=1","favicon":"https://zdnet.co.kr/news/favicon.ico","elements":[{"title":"여기어때, 국제표준 정보보안 경영시스템 4종 인증 갱신","contents":"여행·여가 플랫폼 여기어때(대표 정명훈)가 국제표준 정보보안 경영시스템(ISO) 4종에 대한 인증을 갱신했다고 29일 밝혔다. 이번 인증으로 온라인 숙박 예약 서비스 보안 관리...","link":"https://zdnet.co.kr/view/?no=20230829093249","retrieved":1693269763479,"image":"https://image.zdnet.co.kr/2023/08/29/c94189956bc60af418d5e69b533948fd-290x182.jpg"},{"title":"브랜드엑스코퍼레이션 젝시믹스, '인터텍스타일 상하이 2023' 참석","contents":"미디어커머스 기업 브랜드엑스코퍼레이션(각자대표 이수연, 강민준)이 전개하는 액티브웨어 브랜드 젝시믹스는 효성티앤씨와 함께 세계 최대 섬유 전시회 '인터텍스타일 상하이 2023'...","link":"https://zdnet.co.kr/view/?no=20230829092702","retrieved":1693269763486,"image":"https://image.zdnet.co.kr/2023/08/29/98e1ab3dc4200706419f404571e7a8c4-290x182.jpg"},{"title":"뉴패러다임인베스트먼트, 유망 테크 스타트업 추가 모집","contents":"국내 스타트업들에게 50억원 이상 투자와 자금지원이 가능한 길이 열린다. 뉴패러다임인베스트먼트(공동대표 배상승,박제현)가 올 하반기에 기업당 50억원 이상 투자와 자금지원을 받...","link":"https://zdnet.co.kr/view/?no=20230829091957","retrieved":1693269763489,"image":"https://zdnet.co.kr/images/default.png?ver=20220905"},{"title":"연·고대 실전창업학회 인사이더스, 데모데이 성황리 끝내","contents":"올해 12주년을 맞는 고려대·연세대 연합 실전창업학회 인사이더스가 얼마 전 드림플러스 강남 이벤트홀에서 24기 데모데이를 열었다고 29일 밝혔다. 2011년 설립된 인사이더스는...","link":"https://zdnet.co.kr/view/?no=20230829085444","retrieved":1693269763495,"image":"https://zdnet.co.kr/images/default.png?ver=20220905"},{"title":"젝시믹스, 선셋 요가클래스 성료…\"요가 문화 선도\"","contents":"미디어커머스 기업 브랜드엑스코퍼레이션(각자대표 이수연, 강민준)이 전개하는 액티브웨어 브랜드 젝시믹스는 지난 26일 진행한 '선셋 요가 클래스'를 성황리에 마무리했다고 28일 ...","link":"https://zdnet.co.kr/view/?no=20230828204623","retrieved":1693225243294,"image":"https://zdnet.co.kr/images/default.png?ver=20220905"},{"title":"팀민트, 마케팅 데이터 솔루션 새 기능 선봬","contents":"애드테크 스타트업 팀민트(대표 한만형)는 지난 23일 부산 벡스코에서 개최된 '2023 부산국제마케팅광고제'에 부스로 참가, ReFit 서비스 소개와 새로운 기능인 'AI 시그...","link":"https://zdnet.co.kr/view/?no=20230828190538","retrieved":1693221012945,"image":"https://zdnet.co.kr/images/default.png?ver=20220905"},{"title":"오늘의집, '오!시즌위크' 할인 행사 한 번 더한다","contents":"오늘의집은 연중 최대 쇼핑 축제 '오!시즌위크'(이하 오시즌위크) 기간 동안 고객의 뜨거운 성원에 보답하는 의미로 이달 31일까지 대규모 앙코르 세일을 진행한다. 앙코르 세일 ...","link":"https://zdnet.co.kr/view/?no=20230828165424","retrieved":1693210478193,"image":"https://zdnet.co.kr/images/default.png?ver=20220905"},{"title":"\"옷 좀 덜 사고, 여행\"...와디즈, '이색여행' 펀딩 주목","contents":"코로나19 보복 소비로 명품 시장을 중심으로 호황을 누린 패션업계 주춤하고, 국내외 여행 및 캠핑 등 야외활동 수요가 늘고 있는 것으로 나타났다. 라이프디자인 펀딩플랫폼 와디즈...","link":"https://zdnet.co.kr/view/?no=20230828133420","retrieved":1693199461500,"image":"https://zdnet.co.kr/images/default.png?ver=20220905"},{"title":"소프트뱅크벤처스, 수익실현 확실한 기술혁신 기업에 300억 투자한다","contents":"소프트뱅크벤처스가 약 300억원 규모의 '에스브이에이 2023 세컨더리 투자조합'을 결성했다고 28일 밝혔다. 이번 펀드는 소프트뱅크벤처스의 첫 세컨더리펀드로 최대주주 변동 이...","link":"https://zdnet.co.kr/view/?no=20230828092349","retrieved":1693189112865,"image":"https://zdnet.co.kr/images/default.png?ver=20220905"},{"title":"\"식자재 유통 산업의 혁신 아이콘이 될래요\"","contents":"꿈은 삶의 이정표이자 동력이다. 꿈은 곧 미래의 삶이다. 꿈은 그래서 소중하다. 꿈은 사람마다 다르고 다른 만큼 다채롭다. 스타트업이 꾸는 꿈도 그럴 것이다. 소중하고 다채롭다...","link":"https://zdnet.co.kr/view/?no=20230828093350","retrieved":1693187162362,"image":"https://zdnet.co.kr/images/default.png?ver=20220905"},{"title":"SDT, 양자컴퓨터 클라우드 구축···\"누구나 쉽게 이용\"","contents":"국내 기술로 만든 양자 컴퓨터에 연구자들이 국내 스타트업이 구축한 클라우드 환경에서 편리하게 접속해 이용할 수 있게 된다. 현재 양자 컴퓨터 분야 글로벌 기업들은 클라우드 방식...","link":"https://zdnet.co.kr/view/?no=20230825154734","retrieved":1693196000389,"image":"https://zdnet.co.kr/images/default.png?ver=20220905"},{"title":"잡코리아, '신성장 산업 중소기업 온라인 채용박람회' 개최","contents":"잡코리아는 서울지방중소벤처기업청이 주최하는 '2023 하반기 수도권 신성장 산업분야 중소기업 온라인 채용박람회'를 9월30일까지 개최한다고 밝혔다. 이번 채용박람회는 수도권 소...","link":"https://zdnet.co.kr/view/?no=20230828092104","retrieved":1693183403132,"image":"https://zdnet.co.kr/images/default.png?ver=20220905"},{"title":"SBA, 서울게임콘텐츠센터 입주기업 모집","contents":"서울경제진흥원(대표 김현우, SBA)은 서울의 중소 게임기업 인큐베이팅을 통한 글로벌 유망기업으로 성장지원을 위해 지난 25일부터 약 3주간 서울게임콘텐츠센터 새 입주기업을 모...","link":"https://zdnet.co.kr/view/?no=20230828085128","retrieved":1693183403134,"image":"https://zdnet.co.kr/images/default.png?ver=20220905"},{"title":"오르조 운영사 슬링, '구글 포 스타트업 프로그램' 선정","contents":"에듀테크 기업 슬링(대표 안강민)이 '2023 구글 포 스타트업 클라우드 크레딧 프로그램'에 선정됐다고 25일 밝혔다. 구글 포 스타트업 클라우드 크레딧 프로그램은 구글이 시리...","link":"https://zdnet.co.kr/view/?no=20230825154653","retrieved":1692947443377,"image":"https://zdnet.co.kr/images/default.png?ver=20220905"},{"title":"비욘드테크, '미어캣' MDM 개발 공급","contents":"비욘드테크(대표 박건영)는 업무용 기기를 일괄적으로 관리하고 보안성을 갖춰 회사의 사용 정책을 손쉽게 배포할 수 있는 '미어캣(Meerkat) MDM(Mobile Device ...","link":"https://zdnet.co.kr/view/?no=20230825144502","retrieved":1692944022942,"image":"https://zdnet.co.kr/images/default.png?ver=20220905"},{"title":"서울경제진흥원, 창업자 정신건강 챙긴다","contents":"서울경제진흥원(대표 김현우, SBA)은 '서울창업허브 성수'에서 스타트업 창업자 및 임직원을 대상으로 하는 멘탈케어 프로그램을 지원한다고 25일 밝혔다. 서울창업허브 성수는 입...","link":"https://zdnet.co.kr/view/?no=20230825105240","retrieved":1692929884536,"image":"https://zdnet.co.kr/images/default.png?ver=20220905"},{"title":"원티드랩, '대기업 전용관' 운영","contents":"HR테크 기업 원티드랩은 '대기업 전용관'(이하 전용관)을 운영한다고 25일 밝혔다. 우수 인재 확보를 위해 수시채용에 적극 나서고 있는 대기업과 구직자들을 연결한다는 취지다....","link":"https://zdnet.co.kr/view/?no=20230825090246","retrieved":1692924084912,"image":"https://zdnet.co.kr/images/default.png?ver=20220905"},{"title":"클룩, 홍콩 왕복 무료 항공권 400장 쏜다","contents":"클룩이 홍콩 에어라인과 함께 약 1억2천만원 상당의 홍콩 왕복 항공권 400장을 무료로 제공하는 '공짜 홍콩은 못 참지' 행사를 실시한다고 25일 밝혔다. 홍콩은 코로나19 이...","link":"https://zdnet.co.kr/view/?no=20230825090821","retrieved":1692924084914,"image":"https://zdnet.co.kr/images/default.png?ver=20220905"},{"title":"日 후쿠시마 오염수 방류 우려에...소금·냉동수산물·해조류 거래↑","contents":"일본 후쿠시마 오염수 방류 불안에 온라인에서 살 수 있는 소금, 냉동 수산물, 해조류/건어물의 거래액이 급증한 것으로 나타났다. 이커머스 전문기업 커넥트웨이브(대표집행임원 이건...","link":"https://zdnet.co.kr/view/?no=20230825085408","retrieved":1692924084920,"image":"https://zdnet.co.kr/images/default.png?ver=20220905"},{"title":"뉴패러다임인베스트먼트, '커버링' 프리A 투자","contents":"뉴패러다임인베스트먼트(공동대표 배상승·박제현)가 편리하면서도 지속가능한 생활폐기물 방문수거 솔루션을 전개하는 커버링에 프리A 투자했다고 24일 밝혔다. 커버링은 뉴패러다임의 2...","link":"https://zdnet.co.kr/view/?no=20230824175755","retrieved":1692868298971,"image":"https://zdnet.co.kr/images/default.png?ver=20220905"}]}