{"title":"지디넷코리아 ─ 뉴스 ─ 컴퓨팅","url":"https://zdnet.co.kr/news/?lstcode=0020&page=1","favicon":"https://zdnet.co.kr/news/favicon.ico","elements":[{"title":"당근머니로 24시간 ATM 출금...쿠콘, 'COATM' API 제공","contents":"전국 3만여 개 편의점 ATM에서 365일 24시간 당근페이 출금 서비스를 이용할 수 있게 됐다. 쿠콘(대표 김종현)은 당근페이 ATM 출금 서비스에 'COATM' API를 제...","link":"https://zdnet.co.kr/view/?no=20250319122521","retrieved":1742357738926,"image":"https://zdnet.co.kr/images/default.png?ver=20220905"},{"title":"엔비디아, 구글과 협력해 AI 판도 재편…옴니버스로 '피지컬 AI' 혁신한다","contents":"엔비디아가 인공지능(AI) 추론, 기상 예측, 피지컬 AI 기반 산업 자동화 기술을 종합적으로 혁신하고 있다. 오픈소스 소프트웨어와 협력 이니셔티브를 통해 반도체 강자로서의 입...","link":"https://zdnet.co.kr/view/?no=20250319112745","retrieved":1742354756137,"image":"https://zdnet.co.kr/images/default.png?ver=20220905"},{"title":"라이언로켓, AI 시대 콘텐츠 보호 방안 제시","contents":"라이언로켓이 생성형 인공지능(AI) 시대 콘텐츠 저작권 보호 방안을 제시한다. 라이언로켓 이광섭 경영그룹장은 오는 21일까지 한국콘텐츠진흥원 CKL 기업지원센터에서 열리는 세계...","link":"https://zdnet.co.kr/view/?no=20250319113831","retrieved":1742354756146,"image":"https://zdnet.co.kr/images/default.png?ver=20220905"},{"title":"자사주 모은 신장호 노력 통했나…지난해 주총서 '반성문' 읊던 이 기업, 멍에 벗었다","contents":"3년 연속 감사보고서를 늦게 제출해 지난해 투자주의 환기 종목으로 지정됐던 아이티센엔텍(옛 쌍용정보통신)이 올해 멍에를 벗고 기업 신뢰도 회복을 위한 드라이브를 걸었다. 신장호...","link":"https://zdnet.co.kr/view/?no=20250319112159","retrieved":1742354756147,"image":"https://zdnet.co.kr/images/default.png?ver=20220905"},{"title":"세일즈포스, 디오임플란드에 솔루션 공급…글로벌 시장 경쟁력↑","contents":"세일즈포스가 자사 솔루션을 디오임플란트에 제공해 영업 프로세스 표준화·고객 데이터 분석 강화를 지원했다. 세일즈포스는 디오임플란트가 세일즈포스 솔루션 기반으로 영업 데이터를 통...","link":"https://zdnet.co.kr/view/?no=20250319110812","retrieved":1742354756148,"image":"https://zdnet.co.kr/images/default.png?ver=20220905"},{"title":"어도비, 'AI 에이전트'로 콘텐츠 제작 경쟁력 높인다","contents":"어도비가 인공지능(AI) 에이전트를 앞세워 마케팅 콘텐츠 경쟁력 높이기에 나섰다. 어도비는 '어도비 익스피리언스 플랫폼(AEP)'에 에이전트 기반 AI 기능을 탑재하고 브랜드 ...","link":"https://zdnet.co.kr/view/?no=20250319112303","retrieved":1742354756150,"image":"https://zdnet.co.kr/images/default.png?ver=20220905"},{"title":"오라클, '자바 24'에 AI·양자 내성 보안 추가…OCI와 연동","contents":"오라클이 프로그래밍 언어·개발 플랫폼 '자바 24'를 출시해 개발자 생산성과 보안을 한층 높였다. 오라클은 오라클이 자바 최신 버전 자바 24를 공개했다고 19일 발표했다. 자...","link":"https://zdnet.co.kr/view/?no=20250319105433","retrieved":1742351068182,"image":"https://zdnet.co.kr/images/default.png?ver=20220905"},{"title":"美 경제성장 비결은 '우수 인재'…\"韓도 해외 AI 인력 유치 적극 나서야\"","contents":"최근 전 세계적으로 인공지능(AI) 등 첨단 산업 분야를 중심으로 우수 인력 쟁탈전이 치열해진 가운데 우리나라도 미국처럼 해외 인력 유치에 적극 나설 필요가 있다는 지적이 나왔...","link":"https://zdnet.co.kr/view/?no=20250319110023","retrieved":1742351068186,"image":"https://zdnet.co.kr/images/default.png?ver=20220905"},{"title":"구글, 제미나이에 '캔버스' 도입…오픈AI·앤트로픽 따라잡기 나섰다","contents":"구글이 자사 인공지능(AI) 챗봇에 사용자의 문서·코딩 작업을 지원하는 기능을 선보인다. 오픈AI와 앤트로픽이 먼저 선보인 협업 도구를 뒤따르는 움직임으로, AI 생산성 시장 ...","link":"https://zdnet.co.kr/view/?no=20250319101711","retrieved":1742351068188,"image":"https://zdnet.co.kr/images/default.png?ver=20220905"},{"title":"가상화 솔루션 '오픈스택잇' 질주···공공과 민간서 잇달아 도입","contents":"클라우드 컴퓨팅 및 디지털전환(DT) 전문기업 이노그리드(대표 김명진)는 자사의 가상화 솔루션 '오픈스택잇(Openstackit)'이 클라우드 가상화 표준을 제시하며 주요 공공...","link":"https://zdnet.co.kr/view/?no=20250319103857","retrieved":1742351068190,"image":"https://zdnet.co.kr/images/default.png?ver=20220905"},{"title":"퓨어스토리지, 엔비디아 AI 데이터 플랫폼 통합…스토리지 '강화'","contents":"퓨어스토리지가 엔비디아 인공지능(AI) 데이터 플랫폼을 자사 솔루션에 통합해 스토리지 기술을 한층 강화한다. 퓨어스토리지는 엔터프라이즈급 확장형 AI 지원 솔루션을 고객에게 제...","link":"https://zdnet.co.kr/view/?no=20250319102754","retrieved":1742351068194,"image":"https://zdnet.co.kr/images/default.png?ver=20220905"},{"title":"'양자 오류, AI로 해결한다'…엔비디아, '가속양자연구센터' 공개","contents":"엔비디아가 인공지능(AI) 슈퍼컴퓨터와 양자컴퓨팅을 통합한 차세대 가속 양자 슈퍼컴퓨터 개발에 나섰다. 고성능 AI 인프라를 활용해 양자 오류 수정과 하드웨어 개발을 지원함으로...","link":"https://zdnet.co.kr/view/?no=20250319093901","retrieved":1742351068198,"image":"https://zdnet.co.kr/images/default.png?ver=20220905"},{"title":"지코어-미란티스, AI 모델 배포 효율성 강화 협력","contents":"지코어가 인공지능(AI) 추론 워크로드 배포 효율성을 높이기에 나섰다. 지코어가 오는 21일까지 미국 새너자이에서 열리는 AI 컨퍼런스 'GTC 2025'에서 미란티스와 협력한...","link":"https://zdnet.co.kr/view/?no=20250319094419","retrieved":1742351068200,"image":"https://zdnet.co.kr/images/default.png?ver=20220905"},{"title":"LG CNS, '3D 모바일 셔틀' 앞세워 북미 물류시장 정조준…창고 자동화 혁신","contents":"LG CNS가 창고 자동화 물류로봇을 앞세워 북미 물류자동화 시장 진출에 나선다. LG CNS는 미국 시카고 맥코믹 플레이스에서 열린 세계 최대 물류자동화 전시회 '프로맷(Pr...","link":"https://zdnet.co.kr/view/?no=20250319101704","retrieved":1742351068201,"image":"https://zdnet.co.kr/images/default.png?ver=20220905"},{"title":"SK C&C, 반송 물류 자동화로 글로벌 제조 AI 사업 진출","contents":"SK C&amp;C(대표 윤풍영)가 자체 개발한 '인공지능(AI) 반송 물류 시스템'을 앞세워 미국, 유럽 등 글로벌 제조 AI 시장 공략에 나선다. 실시간 데이터 분석과 자율이동로봇...","link":"https://zdnet.co.kr/view/?no=20250319100742","retrieved":1742351068203,"image":"https://zdnet.co.kr/images/default.png?ver=20220905"},{"title":"720兆 '스타게이트' 이끄는 오픈AI, 첫 데이터센터에 엔비디아 AI 칩 40만개 투입하나","contents":"일본 소프트뱅크, 오라클과 손잡고 '스타게이트' 프로젝트를 추진 중인 오픈AI가 첫 번째 데이터센터 단지에 엔비디아의 인공지능(AI) 칩을 최대 40만 개까지 수용할 수 있는 ...","link":"https://zdnet.co.kr/view/?no=20250319080443","retrieved":1742346012652,"image":"https://zdnet.co.kr/images/default.png?ver=20220905"},{"title":"\"삼성SDS도 신뢰한 AI 팩토리\"…델-엔비디아, 기업용 AI 시장 공략 '박차'","contents":"델 테크놀로지스가 엔비디아와 손잡고 인공지능(AI) 인프라를 전면 업그레이드한다. 기업들의 AI 도입 장벽을 낮추고 혁신 속도를 끌어올려 시장 경쟁력을 강화하려는 행보다. 델 ...","link":"https://zdnet.co.kr/view/?no=20250318111326","retrieved":1742346012655,"image":"https://zdnet.co.kr/images/default.png?ver=20220905"},{"title":"[유미's 픽] \"삼성부터 스타트\"…주총 시즌 돌입한 대기업 SI, 수장들 어떤 말 꺼낼까","contents":"삼성SDS를 시작으로 대기업 IT 계열사들의 주주총회 시즌이 본격 개막한 가운데 올해 수장으로 올라선 신임 대표들이 어떤 메시지를 내놓을 지 주목된다. 인공지능(AI) 시장 확...","link":"https://zdnet.co.kr/view/?no=20250318175753","retrieved":1742339568145,"image":"https://zdnet.co.kr/images/default.png?ver=20220905"},{"title":"\"AI 에이전트 시대 주도\"…엔비디아, 추론 강화 돕는 SW 공개","contents":"엔비디아가 인공지능(AI) 에이전트 시대 본격화를 위한 기술 로드맵을 공개했다. AI 에이전트 개발·유지에 필요한 소프트웨어(SW) 기술을 비롯한 오픈소스 추론 모델 시리즈, ...","link":"https://zdnet.co.kr/view/?no=20250318161053","retrieved":1742328836142,"image":"https://zdnet.co.kr/images/default.png?ver=20220905"},{"title":"\"손·발 달린 AI\"…엔비디아, 로봇·자율주행 위한 '물리 AI' 본격화","contents":"엔비디아가 '피지컬 인공지능(AI)' 기술을 앞세워 로보틱스·자율주행·의료 산업 공략에 나선다. 시뮬레이션과 합성 데이터를 결합함으로써 AI가 물리적 환경에서 직접 행동하는 시...","link":"https://zdnet.co.kr/view/?no=20250319001453","retrieved":1742328836142,"image":"https://zdnet.co.kr/images/default.png?ver=20220905"}]}