{"title":"지디넷코리아 ─ 뉴스 ─ 최신 뉴스","url":"https://zdnet.co.kr/news/?lstcode=0000&page=1","favicon":"https://zdnet.co.kr/news/favicon.ico","elements":[{"title":"뉴렐릭, 익스플로잇 공격 검증 리포팅 기능 정식 출시","contents":"가시성 플랫폼 기업 뉴렐릭은 애플리케이션 보안 테스팅을 위한 익스플로잇 공격 검증 리포팅 기능 등 뉴렐릭 인터랙티브 애플리케이션 보안 테스트(IAST)의 신규 기능을 18일 출...","link":"https://zdnet.co.kr/view/?no=20240318111516","retrieved":1710728175554,"image":"https://image.zdnet.co.kr/2024/03/18/53c139434b2c68805aff3ef0e3bb2c3a-290x182.png"},{"title":"알스퀘어베트남, 상업용 부동산 인테리어 사업 본격 시작","contents":"알스퀘어의 베트남 법인 알스퀘어베트남(지사장 신지민)이 베트남 상업용 부동산 인테리어 사업에 본격 나선다. 18일 알스퀘어에 따르면 알스퀘어베트남은 법인 설립과 이전 컨설팅, ...","link":"https://zdnet.co.kr/view/?no=20240318111205","retrieved":1710728175556,"image":"https://image.zdnet.co.kr/2024/03/18/464f97007657ecedd75cb3e463c76c4f-290x182.jpg"},{"title":"[이번 주 안주] 옷만 '복고'? 우유도 복고풍으로 진행시켜!","contents":"지디넷코리아는 매주 월요일 새롭게 출시된 먹거리 중에서 안주로 먹기 좋은 음식들을 소개합니다. 지나치게 짧은 주말을 보내고 '월요병'을 앓고 있다면 월요일 저녁 안주와 함께 한...","link":"https://zdnet.co.kr/view/?no=20240318105320","retrieved":1710728175557,"image":"https://zdnet.co.kr/images/default.png?ver=20220905"},{"title":"\"크고 무거워도 괜찮아\"...고성능 '괴물노트북' 뜬다","contents":"크기와 성능을 극단적으로 향상시킨 '괴물노트북'의 판매 비중이 시장에서 점차 증가하고 있는 것으로 나타났다. 커넥트웨이브(대표집행임원 이건수) 가격비교 서비스 다나와는 최근 게...","link":"https://zdnet.co.kr/view/?no=20240318110053","retrieved":1710728175559,"image":"https://zdnet.co.kr/images/default.png?ver=20220905"},{"title":"\"전기차 화재 걱정 끝\"…현대차·기아, 첨단 소방기술 개발","contents":"현대자동차·기아가 정부 및 학계와 손잡고 전기차 안전 강화에 나섰다. 현대차·기아는 18일 서울시 서초구에 위치한 엘타워에서 현대차·기아, 소방청(소방연구원), 한국자동차공학회...","link":"https://zdnet.co.kr/view/?no=20240318102436","retrieved":1710728175562,"image":"https://zdnet.co.kr/images/default.png?ver=20220905"},{"title":"삼성 사운드바, 금액·수량 모두 '10년 연속 글로벌 판매 1위' 달성","contents":"삼성전자가 사운드바 시장에서 금액·수량 기준으로 10년 연속 글로벌 판매 1위를 기록했다. 삼성전자는 18년 연속 글로벌 TV 시장 1위에 이어 사운드바 시장에서도 업계 선두를...","link":"https://zdnet.co.kr/view/?no=20240318093924","retrieved":1710728175563,"image":"https://zdnet.co.kr/images/default.png?ver=20220905"},{"title":"넥슨 '빈딕투스: 디파잉 페이트', 마영전이 하드코어를 만났을 때","contents":"넥슨이 지난 14일부터 글로벌 게임 플랫폼 스팀을 통해 신작 액션 RPG '빈딕투스: 디파잉 페이트(빈딕투스)'의 프리 알파 테스트를 시작했다. 빈딕투스는 넥슨 대표 지식재산권...","link":"https://zdnet.co.kr/view/?no=20240318105831","retrieved":1710728175565,"image":"https://zdnet.co.kr/images/default.png?ver=20220905"},{"title":"코바코, 비상임이사 3명 임명","contents":"한국방송광고진흥공사는 공공기관의 운영에 관한 법률에 따라 기획재정부가 온종훈, 이경락, 유재기 씨를 비상임이사로 임명했다고 18일 밝혔다. 비상임이사의 임기는 2년이다....","link":"https://zdnet.co.kr/view/?no=20240318105722","retrieved":1710728175569,"image":"https://zdnet.co.kr/images/default.png?ver=20220905"},{"title":"KINX, 2024년 신입·경력사원 공개 채용 진행","contents":"KINX(대표 김지욱)는 2024년 신입 및 경력사원 공개 채용을 진행한다고 18일 밝혔다. KINX는 이번 2024년 공개 채용을 통해 11개 직무에서 인재를 영입한다. 신입...","link":"https://zdnet.co.kr/view/?no=20240318105638","retrieved":1710728175571,"image":"https://zdnet.co.kr/images/default.png?ver=20220905"},{"title":"채널톡, 채팅 상담용 화상 서비스 '미트' 출시","contents":"채널코퍼레이션(공동대표 최시원·김재홍)이 올인원 AI 메신저 '채널톡'에 음성 및 영상 통화 서비스 '미트'를 출시했다고 18일 밝혔다. 이에 채널톡은 기존의 채팅, 이메일, ...","link":"https://zdnet.co.kr/view/?no=20240318105552","retrieved":1710728175572,"image":"https://zdnet.co.kr/images/default.png?ver=20220905"},{"title":"LG헬로비전, 휴먼 다큐 '눈에 띄는 그녀들 시즌5' 첫 방송","contents":"LG헬로비전은 지역채널 오리지널 휴먼 다큐멘터리 '눈에 띄는 그녀들 시즌5'를 18일 오후 7시에 첫 방송한다고 밝혔다. 프로그램은 PP 8개사와 공동 제작한 것으로 LG헬로비...","link":"https://zdnet.co.kr/view/?no=20240318105433","retrieved":1710728175573,"image":"https://zdnet.co.kr/images/default.png?ver=20220905"},{"title":"가비아, 세계보안엑스포서 DaaS와 공공기관용 IaaS 전시","contents":"가비아(대표 김홍국)는 통합보안 전시회 'SECON &amp; eGISEC 2024'에서 가상 데스크톱 '가비아 DaaS'와 '공공기관 전용 클라우드(IaaS)'를 선보인다고 18일 ...","link":"https://zdnet.co.kr/view/?no=20240318105332","retrieved":1710728175581,"image":"https://zdnet.co.kr/images/default.png?ver=20220905"},{"title":"'폭발위험 없는 배터리 \"성큼\"","contents":"폭발·화재 위험 없는 전고체전지 상용화에 한 걸음 다가선 새로운 공정 기술이 개발됐다. 차세대 휴대폰 배터리 활용 가능성을 높인 연구 결과물이다. 한국전기연구원(KERI) 은 ...","link":"https://zdnet.co.kr/view/?no=20240318105300","retrieved":1710728175582,"image":"https://zdnet.co.kr/images/default.png?ver=20220905"},{"title":"AWS, 멕시코에 50억 달러 들여 데이터센터 건설하는 까닭은?","contents":"본국과 가까운 국가로 사업을 이전하는 '니어쇼어링'이 심화하는 추세다. 실제 아마존웹서비스(AWS)는 멕시코에 진출한 이래로 최다 투자를 결정하며 데이터 센터를 짓겠다는 구상이...","link":"https://zdnet.co.kr/view/?no=20240318091045","retrieved":1710728175585,"image":"https://zdnet.co.kr/images/default.png?ver=20220905"},{"title":"장영진 전 산업부 차관, 무역보험공사 사장 취임","contents":"장영진 전 산업통상자원부 차관이 18일 한국무역보험공사 사장으로 취임했다. 장영진 신임사장은 이날 취임사에서 “글로벌 저성장 기조 속 지정학적 위기와 주요 선진국 간 무역 패권...","link":"https://zdnet.co.kr/view/?no=20240318105134","retrieved":1710728175586,"image":"https://zdnet.co.kr/images/default.png?ver=20220905"},{"title":"[유미's 픽] \"드디어 움직인다\"…'MSP 대어' 메가존, IPO 주관사 선정 작업 착수","contents":"국내 클라우드 관리 서비스 사업자(MSP) 업계 최초로 유니콘 기업에 오른 메가존클라우드가 기업공개(IPO) 추진을 위한 본격적인 움직임에 드디어 돌입한다. 18일 업계에 따르...","link":"https://zdnet.co.kr/view/?no=20240315155412","retrieved":1710728175586,"image":"https://zdnet.co.kr/images/default.png?ver=20220905"},{"title":"대동, 아프리카 섬나라 카보베르데에 농기계 기증","contents":"대동그룹의 미래농업 플랫폼 기업 대동이 아프리카 카보베르데의 농산업 인프라 구축을 위해 트랙터, 경운기 등 2억 원 상당의 농기계 기증을 추진했다고 18일 밝혔다. 카보베르데는...","link":"https://zdnet.co.kr/view/?no=20240318105040","retrieved":1710728175588,"image":"https://zdnet.co.kr/images/default.png?ver=20220905"},{"title":"'나이트크로우 글로벌' 흥행에 신작 준비...위메이드 바쁜 행보","contents":"위메이드가 게임 및 위믹스 사업에 드라이브를 걸고 있다. 이 회사는 MMORPG '나이트크로우 글로벌' 흥행에 이어 신작 모바일 야구게임 '판타스틱 베이스볼'과 MMORPG '...","link":"https://zdnet.co.kr/view/?no=20240318095220","retrieved":1710728175589,"image":"https://zdnet.co.kr/images/default.png?ver=20220905"},{"title":"UAE, 오픈AI 'AI 반도체 개발 투자'...국가 경쟁 본격화","contents":"인공지능(AI)을 둘러싼 경쟁이 국가단위 대규모 투자 경쟁으로 이어질 전망이다. 최근 엣지미들이스트 등 외신에 따르면 아랍에미리트(UAE) 국영 투자사 MGX가 오픈AI의 AI...","link":"https://zdnet.co.kr/view/?no=20240318094701","retrieved":1710728175590,"image":"https://zdnet.co.kr/images/default.png?ver=20220905"},{"title":"메이크스타, 지난해 매출 956억·영업익 30억원 달성","contents":"메이크스타가 국내외 K팝 팬들을 적극 공략한 덕분에 2023년 매출 956억원을 달성하며 전년 대비 100% 성장을 이뤘다. 메이크스타는 해마다 가파른 성장세를 그리고 있다. ...","link":"https://zdnet.co.kr/view/?no=20240318104621","retrieved":1710728175592,"image":"https://zdnet.co.kr/images/default.png?ver=20220905"}]}