{"title":"지디넷코리아 ─ 뉴스 ─ 최신 뉴스","url":"https://zdnet.co.kr/news/?lstcode=0000&page=1","favicon":"https://zdnet.co.kr/news/favicon.ico","elements":[{"title":"에코백스, 로봇청소기 '디봇 N30 프로 옴니' 출시","contents":"로봇가전 전문 브랜드 에코백스는 먼지 엉킴 현상을 최소화한 신제품 '디봇 N30 프로 옴니'를 출시했다고 14일 밝혔다. 제품은 최신 기술 '제로탱글 2.0' 기술을 적용해 트...","link":"https://zdnet.co.kr/view/?no=20241014150927","retrieved":1728886676052,"image":"https://image.zdnet.co.kr/2024/10/14/83d78f616936d029040f54df0073b16e-290x182.jpg"},{"title":"고팍스, 정보보호관리체계(ISMS) 인증 갱신 완료","contents":"고팍스(대표 조영중)는 정보보호 관리체계(ISMS) 인증 갱신을 완료했다고 14일 밝혔다. 지난 2018년 ISMS 인증을 가상거래소업계 최초 획득한 고팍스는 최근 진행된 갱신...","link":"https://zdnet.co.kr/view/?no=20241014150711","retrieved":1728886676055,"image":"https://image.zdnet.co.kr/2023/11/21/439a4fbdf85ab69094a8840307e8f4e0-290x182.jpg"},{"title":"카카오게임즈, '로스트 아이돌론스 위선의 마녀' 11월 글로벌 얼리액세스","contents":"카카오게임즈(대표 한상우)는 14일 오션드라이브 스튜디오(대표 김희재)가 개발 중인 RPG '로스트 아이돌론스: 위선의 마녀'의 스팀 얼리 액세스(앞서 해보기) 버전 출시일을 ...","link":"https://zdnet.co.kr/view/?no=20241014150219","retrieved":1728886676057,"image":"https://zdnet.co.kr/images/default.png?ver=20220905"},{"title":"[유통 픽] 겨울 한파 대비…롯데백화점·아울렛 '아우터 페어' 진행 外","contents":"롯데백화점과 롯데아울렛에서 가을·겨울 날씨에 대비하기 위한 대규모 '아우터 페어' 행사를 선보인다. 롯데백화점 전 점에서는 오는 17일부터 27일까지 '아우터 페어' 행사를 진...","link":"https://zdnet.co.kr/view/?no=20241014100446","retrieved":1728886676058,"image":"https://zdnet.co.kr/images/default.png?ver=20220905"},{"title":"\"간호법 제정 끝 아냐…'전문간호사' 행위 법적 근거 필요”","contents":"제11회 한국전문간호사협회 학술대회 및 정책세미나가 지난 13일 오전 서울 송파 소재 서울아산병원 연구원에서 개최됐다. 이번 학술대회 주제는 '간호법 제정 후 전문간호사가 나아...","link":"https://zdnet.co.kr/view/?no=20241014145819","retrieved":1728886676061,"image":"https://zdnet.co.kr/images/default.png?ver=20220905"},{"title":"자라 모회사 인디텍스, 섬유 혁신 자금 조달 펀드 출범","contents":"패션브랜드 자라 모회사인 인디텍스가 섬유 분야 혁신 프로젝트에 5천만 유로(약 738억원)를 투자하는 펀드를 출범했다. 스페인 일간지 엘 컨피덴셜과 로이터통신에 따르면 이번 신...","link":"https://zdnet.co.kr/view/?no=20241014093109","retrieved":1728886676063,"image":"https://zdnet.co.kr/images/default.png?ver=20220905"},{"title":"임영웅 함께한 하나은행 자선축구대회, 3만5천명 모여 성료","contents":"하나은행은 하나금융그룹의 광고모델인 임영웅과 함께 사회취약계층 지원을 위해 개최한 '하나은행 자선축구대회(Hana Bank Charity Match)'가 3만5천여명 관중이 모...","link":"https://zdnet.co.kr/view/?no=20241014145114","retrieved":1728886676065,"image":"https://zdnet.co.kr/images/default.png?ver=20220905"},{"title":"\"삼성 첫 슬림형 폴더블폰, 화면 주름 개선된다\"","contents":"삼성전자가 새롭게 선보일 것으로 전망되는 슬림형 폴더블폰 '갤럭시Z 폴드6 스페셜 에디션'에 대한 정보가 나왔다. IT매체 안드로이드오쏘리티는 최근 유명 IT팁스터 아이스유니버...","link":"https://zdnet.co.kr/view/?no=20241014134455","retrieved":1728886676066,"image":"https://zdnet.co.kr/images/default.png?ver=20220905"},{"title":"\"가상자산 ETF-법인계좌 주목 환영…NFT 외면 우려\"","contents":"금융당국이 가상자산 ETF 국내 도입과 법인 실명계좌 허용에 대해 논의할 계획이라고 밝힘에 따라 관심이 집중된다. 하지만 NFT 문제는 여전히 거론될 기미가 보이지 않고 있어 ...","link":"https://zdnet.co.kr/view/?no=20241014112427","retrieved":1728886676071,"image":"https://zdnet.co.kr/images/default.png?ver=20220905"},{"title":"크래프톤, 배그 모바일 X 베놈: 라스트 댄스 협업 아이템 선보여","contents":"크래프톤(대표 김창한)은 '배틀그라운드 모바일'에 액션 블록버스터 '베놈: 라스트 댄스'의 협업 아이템을 추가할 예정이라고 14일 밝혔다. 베놈: 라스트 댄스는 소니 픽처스가 ...","link":"https://zdnet.co.kr/view/?no=20241014142239","retrieved":1728886676071,"image":"https://zdnet.co.kr/images/default.png?ver=20220905"},{"title":"적자 수협조합 늘었다 지적에 노동진 회장 \"대한민국 자체 문제\"","contents":"단위 수협의 부실이 확대돼 적자인 수협조합이 늘어나고 있다는 지적에 노동진 수협중앙회 회장이 \"대한민국 자체적으로 문제가 생겼다\"며 범국민적 대처를 요구했다. 14일 국회 농림...","link":"https://zdnet.co.kr/view/?no=20241014105859","retrieved":1728886676071,"image":"https://zdnet.co.kr/images/default.png?ver=20220905"},{"title":"한국은행, 120억 차세대 외화자산운용관리시스템 2단계 사업 발주","contents":"한국은행이 급변하는 대외환경에 대응하기 위해 120억 규모의 차세대 외화자산운용관리시스템의 2단계 사업을 발주하며 본격적인 구축에 나선다. 14일 관련 업계에 따르면 한국은행이...","link":"https://zdnet.co.kr/view/?no=20241014142745","retrieved":1728886676073,"image":"https://zdnet.co.kr/images/default.png?ver=20220905"},{"title":"코빗 리서치센터 \"美 대선...어느 후보가 이겨도 비트코인 수요 증가 가능성\"","contents":"코빗(대표 오세진) 산하 코빗 리서치센터가 기관투자자 자금 동향 및 미국 대선의 영향을 다룬 보고서 '기관 자금 동향: Bitcoin Election?'을 발간했다고 14일 밝...","link":"https://zdnet.co.kr/view/?no=20241014143547","retrieved":1728886676074,"image":"https://zdnet.co.kr/images/default.png?ver=20220905"},{"title":"현대차, 노인·아동 이동권 '수요응답교통'으로 지원","contents":"현대자동차는 14일 경찰청, 대한민국시장·군수·구청장협의회와 '고령자 이동권 교통안전 및 이동권 보장을 위한 다자간 업무 협약'을 체결했다고 밝혔다. 이번 업무 협약은 첨단 I...","link":"https://zdnet.co.kr/view/?no=20241014143052","retrieved":1728886676075,"image":"https://zdnet.co.kr/images/default.png?ver=20220905"},{"title":"\"음료 권하고 춤추던 옵티머스 로봇, 사람이 원격 조종\"","contents":"테슬라가 지난 주 개최한 '위, 로봇'(We, Robot) 행사에는 휴머노이드 로봇 '옵티머스'가 등장해 눈길을 끌었다. 옵티머스는 손님들에게 음료나 선물을 제공하고, 춤을 추...","link":"https://zdnet.co.kr/view/?no=20241014110035","retrieved":1728886676079,"image":"https://zdnet.co.kr/images/default.png?ver=20220905"},{"title":"국민연금, MBK 출자금 묶었나…\"고려아연 불똥 방지 목적\"","contents":"고려아연 경영권을 두고 최윤범 고려아연 회장과 영풍·MBK파트너스 연합 간 대립이 격화되는 가운데, 국민연금이 MBK파트너스(이하 MBK)에 출자한 자금을 고려아연 공개매수에 ...","link":"https://zdnet.co.kr/view/?no=20241014131334","retrieved":1728886676081,"image":"https://zdnet.co.kr/images/default.png?ver=20220905"},{"title":"엔씨소프트 리니지W, 첫 아트북 'The art of Lineage W' 출간","contents":"엔씨소프트(공동대표 김택진, 박병무)는 멀티플랫폼 MMORPG(다중접속역할수행게임) '리니지W'의 첫 번째 아트북 'The art of Lineage W'를 출간했다고 14일 ...","link":"https://zdnet.co.kr/view/?no=20241014141726","retrieved":1728886676085,"image":"https://zdnet.co.kr/images/default.png?ver=20220905"},{"title":"넥슨게임즈, '퍼스트 디센던트' 개발력 강화...집중채용 돌입","contents":"넥슨게임즈(대표 박용현)는 차세대 루트슈터 게임 '퍼스트 디센던트'의 라이브 서비스 등 개발 역량 강화를 위해서 '매그넘 스튜디오'의 개발 인력을 집중 채용한다고 14일 밝혔다...","link":"https://zdnet.co.kr/view/?no=20241014141251","retrieved":1728886676085,"image":"https://zdnet.co.kr/images/default.png?ver=20220905"},{"title":"마우저, 차량용 고휘도 프로젝터 위한 TI 평가 모듈 공급","contents":"마우저일렉트로닉스는 자동차 애플리케이션의 프로젝터 개발을 가속화하고 출시시간을 단축할 수 있는 TI(텍사스인스트루먼트)의 'DLP5532PROJHBQ1EVM' 평가 모듈(EVM...","link":"https://zdnet.co.kr/view/?no=20241014133137","retrieved":1728886676086,"image":"https://zdnet.co.kr/images/default.png?ver=20220905"},{"title":"전기안전공사, 캠핑철 전기안전 수칙 공개…릴선 풀고 배전함 청소","contents":"한국전기안전공사(대표 남화영)는 14일 가을철 캠핑장 전기안전 수칙 '톱 3'를 공개했다. '전기릴선 관리' '배전함 관리' '전기주전자 관리'로 구성된 이번 수칙은 가을철 캠...","link":"https://zdnet.co.kr/view/?no=20241014135927","retrieved":1728882758306,"image":"https://zdnet.co.kr/images/default.png?ver=20220905"}]}