{"title":"지디넷코리아 ─ 뉴스 ─ 최신 뉴스","url":"https://zdnet.co.kr/news/?lstcode=0000&page=1","favicon":"https://zdnet.co.kr/news/favicon.ico","elements":[{"title":"2025년도 수가협상, 의사협회 빠진 가운데 시작","contents":"대한의사협회가 불참한 가운데 2025년도 수가협상이 시작됐다. 3일 오전 2025년도 요양급여비용 계약 관련 국민건강보험공단 이사장과 의약단체장 합동 간담회(이하 '수가협상 상...","link":"https://zdnet.co.kr/view/?no=20240503123217","retrieved":1714709614893,"image":"https://image.zdnet.co.kr/2024/05/03/077c1255b752d0600f622c7852e5a3df-290x182.jpg"},{"title":"몽고DB, 아틀라스 스트림 프로세싱 등 신규 기능 출시","contents":"몽고DB는 최근 개최한 연례 개발자 행사인 '몽고DB 닷로컬 뉴욕'에서 최신 애플리케이션을 빠르고 쉽게 구축, 배포 및 실행할 수 있는 몽고DB 아틀라스의 새로운 기능을 발표했...","link":"https://zdnet.co.kr/view/?no=20240503122855","retrieved":1714709614896,"image":"https://image.zdnet.co.kr/2023/06/29/1f67026b54ae887adea67ba408bde853-290x182.jpg"},{"title":"IBM, 한국도 AWS 마켓플레이스로 소프트웨어 제공","contents":"IBM은 한국을 포함한 전 세계 92개국에서 아마존웹서비스(AWS) 마켓플레이스를 통해 공급하는 자사 소프트웨어 포트폴리오를 확대한다고 3일 발표했다. AWS 마켓플레이스는 A...","link":"https://zdnet.co.kr/view/?no=20240503122511","retrieved":1714709614897,"image":"https://zdnet.co.kr/images/default.png?ver=20220905"},{"title":"어도비, 파이어플라이 적용 '어도비 익스프레스' 모바일 앱 출시","contents":"어도비는 파이어플라이 Ai를 적용한 '어도비 익스프레스' 모바일 애플리케이션을 공식 출시한다고 3일 밝혔다. 콘텐츠 크리에이터는 어디서나 어도비 파이어플라이 생성형 AI 구동 ...","link":"https://zdnet.co.kr/view/?no=20240503122058","retrieved":1714709614898,"image":"https://zdnet.co.kr/images/default.png?ver=20220905"},{"title":"에버스핀, '페이크파인더' 케이뱅크 공급…악성앱 피싱범죄 잡는다","contents":"AI 보안기업 에버스핀(대표 하영빈)이 악성앱 피싱방지 솔루션 '페이크파인더'를 케이뱅크에 공급했다고 3일 밝혔다. 케이뱅크의 도입으로 국내 인터넷은행 3사 가운데 카카오뱅크와...","link":"https://zdnet.co.kr/view/?no=20240503121937","retrieved":1714709614900,"image":"https://zdnet.co.kr/images/default.png?ver=20220905"},{"title":"알테어, 전산유체역학 전문기업 '리서치인플라이트' 인수","contents":"알테어는 항공우주 분야에 특화된 전산유체역학(CFD) 소프트웨어 제조사 '리서치인플라이트'를 인수했다고 3일 밝혔다. 리서치인플라이트의 대표 제품 '플라이트스트림'은 높은 정확...","link":"https://zdnet.co.kr/view/?no=20240503121305","retrieved":1714709614902,"image":"https://zdnet.co.kr/images/default.png?ver=20220905"},{"title":"경쟁력 높아진 韓 서브컬처…日 이용자 공략 나선다","contents":"국산 서브컬처 게임의 경쟁력이 점점 커지고 있다. '블루 아카이브'와 '니케: 승리의 여신(니케)' 등이 서브컬쳐 종주국인 일본 시장에서 큰 성공을 거두면서 영향력이 높아졌다는...","link":"https://zdnet.co.kr/view/?no=20240503113040","retrieved":1714705915054,"image":"https://zdnet.co.kr/images/default.png?ver=20220905"},{"title":"\"참가비 수천만원도 괜찮다\"…역대급 'AWS 서밋 서울'에 기업들 몰리는 이유","contents":"올해로 10주년을 맞이하는 국내 최대 규모의 클라우드 기술 컨퍼런스인 'AWS 서밋 서울'에 다수의 국내 기업들이 참가해 아마존웹서비스(AWS)와의 협업 강화에 나선다. AWS...","link":"https://zdnet.co.kr/view/?no=20240503113831","retrieved":1714705915057,"image":"https://zdnet.co.kr/images/default.png?ver=20220905"},{"title":"비트코인 시세 연일 하락세...홍콩 ETF-반감기 종료도 효과無","contents":"반감기 종료 이후 상승세가 이어질 것으로 예상됐던 비트코인 시세가 주춤하다. 홍콩에서 현물 ETF 거래가 개시됨에 따라 긍정적인 영향이 이어질 것이라는 전망이 무색한 수준이다....","link":"https://zdnet.co.kr/view/?no=20240503112723","retrieved":1714705915060,"image":"https://zdnet.co.kr/images/default.png?ver=20220905"},{"title":"美대륙 질주하는 현대차그룹…수소생태계 본격 구축","contents":"현대자동차가 지금까지 쌓아온 친환경차 이미지를 바탕으로 미국에서 수소전기트럭 사업 본격 전개에 나선다. 현대차는 2일(현지시간) 미국 오클랜드에서 미국 친환경 프로젝트 지원 비...","link":"https://zdnet.co.kr/view/?no=20240503114319","retrieved":1714705915065,"image":"https://zdnet.co.kr/images/default.png?ver=20220905"},{"title":"성장통 겪는 SKC, 미래먹거리 키우느라 적자 허덕","contents":"한계 사업 매각 후 신성장동력 키우기에 박차를 가하는 SKC의 성장통이 이어지고 있다. 지난 2022년 4분기부터 6개 분기 연속 적자를 기록 중이다. 이에 올해 설비투자는 전...","link":"https://zdnet.co.kr/view/?no=20240503102829","retrieved":1714705915068,"image":"https://zdnet.co.kr/images/default.png?ver=20220905"},{"title":"우리금융 증권사 10년 만에 부활탄 쐈다","contents":"우리금융그룹이 우리투자증권을 매각한지 10년 만에 증권업에 재진출한다. 3일 우리금융은 이사회를 열고 합병한 우리종합금융(우리종금)과 한국포스증권(포스증권)을 자회사로 편입하기...","link":"https://zdnet.co.kr/view/?no=20240503105806","retrieved":1714705915071,"image":"https://zdnet.co.kr/images/default.png?ver=20220905"},{"title":"ISC, 1분기 매출 351억…전분기比 40% 증가","contents":"반도체 테스트 솔루션 기업 아이에스시(ISC)는 올해 1분기 매출 351억원, 영업이익 86억원(영업이익률 25%)을 기록했다고 밝혔다. 전분기 대비 매출액은 40%, 영업이익...","link":"https://zdnet.co.kr/view/?no=20240503112010","retrieved":1714705915072,"image":"https://zdnet.co.kr/images/default.png?ver=20220905"},{"title":"에코프로, 1Q 매출 50% 줄고 '적자전환'…전기차 '캐즘' 영향","contents":"에코프로가 주요 전방 산업인 전기차 시장 성장 둔화에 따라 올 1분기 실적이 전년 동기 대비 매출은 절반 정도 줄고, 영업이익은 적자전환했다. 에코프로는 올해 1분기 연결기준 ...","link":"https://zdnet.co.kr/view/?no=20240503110830","retrieved":1714703011959,"image":"https://zdnet.co.kr/images/default.png?ver=20220905"},{"title":"달에 간 우주인, 운동 이렇게 하세요 [우주로 간다]","contents":"달과 같은 저중력 환경에서 인간이 오랫동안 생활하면 근육이 위축되고 뼈의 질량이 감소하는 등 신체적 변화를 경험하게 마련이다. 우주과학매체 스페이스닷컴은 이탈리아 밀라노대학 연...","link":"https://zdnet.co.kr/view/?no=20240503105957","retrieved":1714703011969,"image":"https://zdnet.co.kr/images/default.png?ver=20220905"},{"title":"시마크로, 화학공학회 학술대회서 공정 디지털 트윈 응용사례 공유","contents":"시마크로(대표 윤정호)는 한국화학공학회가 제주 국제 컨벤션 센터에서 주최한 '한국화학공학회 봄 총회·학술대회'에서 '화학·바이오 공정 디지털 트윈 응용사례 및 비전 심포지엄'을...","link":"https://zdnet.co.kr/view/?no=20240503111432","retrieved":1714703011972,"image":"https://zdnet.co.kr/images/default.png?ver=20220905"},{"title":"안랩 \"기업 랜섬웨어·보안 위협 증가…'안랩MDS' 관심↑\"","contents":"최근 기업을 노린 랜섬웨어와 알려지지 않은 보안 위협이 증가함에 따라 이를 탐지·대응하는 '안랩MDS'가 주목받고 있다. 안랩(대표 강석균)은 자사 지능형 위협(APT) 대응 ...","link":"https://zdnet.co.kr/view/?no=20240503103233","retrieved":1714703011975,"image":"https://zdnet.co.kr/images/default.png?ver=20220905"},{"title":"이공계 박사취득 재정원천은 주로 '연구과제 인건비'","contents":"국내 학업전념 박사학위 취득 재정원천은 이공계의 경우 주로 '연구과제 인건비'로, 비이공계는 대출이나 개인저축, 부모님 지원에 주로 의존하고 있는 것으로 나타났다. 과학기술정책...","link":"https://zdnet.co.kr/view/?no=20240503111104","retrieved":1714703011977,"image":"https://zdnet.co.kr/images/default.png?ver=20220905"},{"title":"마이크로소프트, 말레이시아에 데이터센터 세운다","contents":"마이크로소프트가 말레이시아에 클라우드와 인공지능(AI) 인프라 구축을 위해 22억 달러(약 86억원)를 투자한다. 이를 통해 동남아시아에서 증가하는 AI 컴퓨팅 수요에 대응할 ...","link":"https://zdnet.co.kr/view/?no=20240503101140","retrieved":1714703011979,"image":"https://zdnet.co.kr/images/default.png?ver=20220905"},{"title":"'내수 정복' 화웨이, 이제 글로벌 노린다…퓨라70 유럽 출시","contents":"화웨이가 글로벌 스마트폰 점유율을 높이기 위해 유럽 시장 공략에 나선다. 2일(현지시간) 폰아레나에 따르면 화웨이는 최근 중국에서 출시한 스마트폰 신제품 퓨라70 시리즈를 유럽...","link":"https://zdnet.co.kr/view/?no=20240503084146","retrieved":1714703011981,"image":"https://zdnet.co.kr/images/default.png?ver=20220905"}]}